{"frame":1710,"sprites":[{"t":1800,"c":2,"s":1,"x":117,"y":146,"fx":true,"fy":false},{"t":1812,"c":2,"s":1,"x":117,"y":178,"fx":true,"fy":false},{"t":1804,"c":2,"s":1,"x":101,"y":146,"fx":true,"fy":false},{"t":1814,"c":2,"s":1,"x":101,"y":178,"fx":true,"fy":false},{"t":2,"c":0,"s":1,"x":83,"y":168,"fx":false,"fy":false},{"t":18,"c":0,"s":1,"x":83,"y":200,"fx":false,"fy":false},{"t":6,"c":0,"s":1,"x":99,"y":168,"fx":false,"fy":false},{"t":20,"c":0,"s":1,"x":99,"y":200,"fx":false,"fy":false},{"t":6048,"c":2,"s":1,"x":35,"y":188,"fx":false,"fy":false},{"t":6050,"c":2,"s":1,"x":35,"y":220,"fx":false,"fy":false},{"t":6052,"c":2,"s":1,"x":51,"y":188,"fx":false,"fy":false},{"t":6054,"c":2,"s":1,"x":51,"y":220,"fx":false,"fy":false},{"t":6056,"c":2,"s":1,"x":67,"y":220,"fx":false,"fy":false}]}
