[{"tile":454,"color":0,"flipX":false,"flipY":false},{"tile":456,"color":0,"flipX":false,"flipY":false},{"tile":455,"color":0,"flipX":false,"flipY":false},{"tile":456,"color":0,"flipX":false,"flipY":false},{"tile":689,"color":2,"flipX":true,"flipY":false},{"tile":690,"color":2,"flipX":true,"flipY":false},{"tile":691,"color":2,"flipX":true,"flipY":false},{"tile":692,"color":2,"flipX":true,"flipY":false},{"tile":689,"color":2,"flipX":true,"flipY":false},{"tile":690,"color":2,"flipX":true,"flipY":false},{"tile":691,"color":2,"flipX":true,"flipY":false},{"tile":692,"color":2,"flipX":true,"flipY":false},{"tile":689,"color":2,"flipX":true,"flipY":false},{"tile":690,"color":2,"flipX":true,"flipY":false},{"tile":691,"color":2,"flipX":true,"flipY":false},{"tile":692,"color":2,"flipX":true,"flipY":false},{"tile":457,"color":0,"flipX":false,"flipY":false},{"tile":458,"color":0,"flipX":false,"flipY":false},{"tile":457,"color":0,"flipX":false,"flipY":false},{"tile":458,"color":0,"flipX":false,"flipY":false},{"tile":693,"color":2,"flipX":true,"flipY":false},{"tile":694,"color":2,"flipX":true,"flipY":false},{"tile":695,"color":2,"flipX":true,"flipY":false},{"tile":696,"color":2,"flipX":true,"flipY":false},{"tile":693,"color":2,"flipX":true,"flipY":false},{"tile":694,"color":2,"flipX":true,"flipY":false},{"tile":695,"color":2,"flipX":true,"flipY":false},{"tile":696,"color":2,"flipX":true,"flipY":false},{"tile":693,"color":2,"flipX":true,"flipY":false},{"tile":694,"color":2,"flipX":true,"flipY":false},{"tile":695,"color":2,"flipX":true,"flipY":false},{"tile":696,"color":2,"flipX":true,"flipY":false},{"tile":460,"color":0,"flipX":false,"flipY":false},{"tile":461,"color":0,"flipX":false,"flipY":false},{"tile":460,"color":0,"flipX":false,"flipY":false},{"tile":461,"color":0,"flipX":false,"flipY":false},{"tile":697,"color":2,"flipX":true,"flipY":false},{"tile":698,"color":2,"flipX":true,"flipY":false},{"tile":699,"color":2,"flipX":true,"flipY":false},{"tile":700,"color":2,"flipX":true,"flipY":false},{"tile":697,"color":2,"flipX":true,"flipY":false},{"tile":698,"color":2,"flipX":true,"flipY":false},{"tile":699,"color":2,"flipX":true,"flipY":false},{"tile":700,"color":2,"flipX":true,"flipY":false},{"tile":697,"color":2,"flipX":true,"flipY":false},{"tile":698,"color":2,"flipX":true,"flipY":false},{"tile":699,"color":2,"flipX":true,"flipY":false},{"tile":700,"color":2,"flipX":true,"flipY":false},{"tile":463,"color":0,"flipX":false,"flipY":false},{"tile":464,"color":0,"flipX":false,"flipY":false},{"tile":463,"color":0,"flipX":false,"flipY":false},{"tile":464,"color":0,"flipX":false,"flipY":false},{"tile":661,"color":2,"flipX":true,"flipY":false},{"tile":661,"color":2,"flipX":true,"flipY":false},{"tile":661,"color":2,"flipX":true,"flipY":false},{"tile":661,"color":2,"flipX":true,"flipY":false},{"tile":661,"color":2,"flipX":true,"flipY":false},{"tile":661,"color":2,"flipX":true,"flipY":false},{"tile":661,"color":2,"flipX":true,"flipY":false},{"tile":661,"color":2,"flipX":true,"flipY":false},{"tile":661,"color":2,"flipX":true,"flipY":false},{"tile":661,"color":2,"flipX":true,"flipY":false},{"tile":661,"color":2,"flipX":true,"flipY":false},{"tile":661,"color":2,"flipX":true,"flipY":false},{"tile":466,"color":0,"flipX":false,"flipY":false},{"tile":467,"color":0,"flipX":false,"flipY":false},{"tile":466,"color":0,"flipX":false,"flipY":false},{"tile":467,"color":0,"flipX":false,"flipY":false},{"tile":671,"color":2,"flipX":true,"flipY":false},{"tile":665,"color":2,"flipX":true,"flipY":false},{"tile":665,"color":2,"flipX":true,"flipY":false},{"tile":666,"color":2,"flipX":true,"flipY":false},{"tile":671,"color":2,"flipX":true,"flipY":false},{"tile":665,"color":2,"flipX":true,"flipY":false},{"tile":665,"color":2,"flipX":true,"flipY":false},{"tile":666,"color":2,"flipX":true,"flipY":false},{"tile":672,"color":2,"flipX":true,"flipY":false},{"tile":673,"color":2,"flipX":true,"flipY":false},{"tile":673,"color":2,"flipX":true,"flipY":false},{"tile":673,"color":2,"flipX":true,"flipY":false},{"tile":470,"color":0,"flipX":false,"flipY":false},{"tile":471,"color":0,"flipX":false,"flipY":false},{"tile":470,"color":0,"flipX":false,"flipY":false},{"tile":471,"color":0,"flipX":false,"flipY":false},{"tile":675,"color":2,"flipX":true,"flipY":false},{"tile":669,"color":2,"flipX":true,"flipY":false},{"tile":669,"color":2,"flipX":true,"flipY":false},{"tile":670,"color":2,"flipX":true,"flipY":false},{"tile":675,"color":2,"flipX":true,"flipY":false},{"tile":669,"color":2,"flipX":true,"flipY":false},{"tile":669,"color":2,"flipX":true,"flipY":false},{"tile":670,"color":2,"flipX":true,"flipY":false},{"tile":682,"color":2,"flipX":true,"flipY":false},{"tile":677,"color":2,"flipX":true,"flipY":false},{"tile":677,"color":2,"flipX":true,"flipY":false},{"tile":677,"color":2,"flipX":true,"flipY":false},{"tile":472,"color":0,"flipX":false,"flipY":false},{"tile":473,"color":0,"flipX":false,"flipY":false},{"tile":472,"color":0,"flipX":false,"flipY":false},{"tile":473,"color":0,"flipX":false,"flipY":false},{"tile":675,"color":2,"flipX":true,"flipY":false},{"tile":669,"color":2,"flipX":true,"flipY":false},{"tile":669,"color":2,"flipX":true,"flipY":false},{"tile":670,"color":2,"flipX":true,"flipY":false},{"tile":675,"color":2,"flipX":true,"flipY":false},{"tile":669,"color":2,"flipX":true,"flipY":false},{"tile":669,"color":2,"flipX":true,"flipY":false},{"tile":670,"color":2,"flipX":true,"flipY":false},{"tile":682,"color":2,"flipX":true,"flipY":false},{"tile":677,"color":2,"flipX":true,"flipY":false},{"tile":677,"color":2,"flipX":true,"flipY":false},{"tile":676,"color":2,"flipX":true,"flipY":false},{"tile":475,"color":0,"flipX":false,"flipY":false},{"tile":476,"color":0,"flipX":false,"flipY":false},{"tile":477,"color":0,"flipX":false,"flipY":false},{"tile":478,"color":0,"flipX":false,"flipY":false},{"tile":675,"color":2,"flipX":true,"flipY":false},{"tile":669,"color":2,"flipX":true,"flipY":false},{"tile":669,"color":2,"flipX":true,"flipY":false},{"tile":670,"color":2,"flipX":true,"flipY":false},{"tile":675,"color":2,"flipX":true,"flipY":false},{"tile":669,"color":2,"flipX":true,"flipY":false},{"tile":669,"color":2,"flipX":true,"flipY":false},{"tile":670,"color":2,"flipX":true,"flipY":false},{"tile":682,"color":2,"flipX":true,"flipY":false},{"tile":676,"color":2,"flipX":true,"flipY":false},{"tile":677,"color":2,"flipX":true,"flipY":false},{"tile":677,"color":2,"flipX":true,"flipY":false},{"tile":480,"color":0,"flipX":false,"flipY":false},{"tile":481,"color":0,"flipX":false,"flipY":false},{"tile":482,"color":0,"flipX":false,"flipY":false},{"tile":483,"color":0,"flipX":false,"flipY":false},{"tile":675,"color":2,"flipX":true,"flipY":false},{"tile":669,"color":2,"flipX":true,"flipY":false},{"tile":669,"color":2,"flipX":true,"flipY":false},{"tile":670,"color":2,"flipX":true,"flipY":false},{"tile":675,"color":2,"flipX":true,"flipY":false},{"tile":669,"color":2,"flipX":true,"flipY":false},{"tile":669,"color":2,"flipX":true,"flipY":false},{"tile":670,"color":2,"flipX":true,"flipY":false},{"tile":484,"color":0,"flipX":false,"flipY":false},{"tile":485,"color":0,"flipX":false,"flipY":false},{"tile":474,"color":0,"flipX":false,"flipY":false},{"tile":474,"color":0,"flipX":false,"flipY":false},{"tile":486,"color":0,"flipX":false,"flipY":false},{"tile":487,"color":0,"flipX":false,"flipY":false},{"tile":488,"color":0,"flipX":false,"flipY":false},{"tile":489,"color":0,"flipX":false,"flipY":false},{"tile":675,"color":2,"flipX":true,"flipY":false},{"tile":669,"color":2,"flipX":true,"flipY":false},{"tile":669,"color":2,"flipX":true,"flipY":false},{"tile":670,"color":2,"flipX":true,"flipY":false},{"tile":675,"color":2,"flipX":true,"flipY":false},{"tile":669,"color":2,"flipX":true,"flipY":false},{"tile":669,"color":2,"flipX":true,"flipY":false},{"tile":670,"color":2,"flipX":true,"flipY":false},{"tile":490,"color":0,"flipX":false,"flipY":false},{"tile":491,"color":0,"flipX":false,"flipY":false},{"tile":479,"color":0,"flipX":false,"flipY":false},{"tile":479,"color":0,"flipX":false,"flipY":false},{"tile":492,"color":0,"flipX":false,"flipY":false},{"tile":493,"color":0,"flipX":false,"flipY":false},{"tile":494,"color":0,"flipX":false,"flipY":false},{"tile":495,"color":0,"flipX":false,"flipY":false},{"tile":679,"color":2,"flipX":true,"flipY":false},{"tile":681,"color":2,"flipX":true,"flipY":false},{"tile":681,"color":2,"flipX":true,"flipY":false},{"tile":680,"color":2,"flipX":true,"flipY":false},{"tile":679,"color":2,"flipX":true,"flipY":false},{"tile":681,"color":2,"flipX":true,"flipY":false},{"tile":681,"color":2,"flipX":true,"flipY":false},{"tile":680,"color":2,"flipX":true,"flipY":false},{"tile":496,"color":0,"flipX":false,"flipY":false},{"tile":497,"color":0,"flipX":false,"flipY":false},{"tile":498,"color":0,"flipX":false,"flipY":false},{"tile":499,"color":0,"flipX":false,"flipY":false},{"tile":655,"color":2,"flipX":true,"flipY":false},{"tile":656,"color":2,"flipX":true,"flipY":false},{"tile":663,"color":2,"flipX":true,"flipY":false},{"tile":664,"color":2,"flipX":true,"flipY":false},{"tile":663,"color":2,"flipX":true,"flipY":false},{"tile":664,"color":2,"flipX":true,"flipY":false},{"tile":663,"color":2,"flipX":true,"flipY":false},{"tile":664,"color":2,"flipX":true,"flipY":false},{"tile":663,"color":2,"flipX":true,"flipY":false},{"tile":664,"color":2,"flipX":true,"flipY":false},{"tile":663,"color":2,"flipX":true,"flipY":false},{"tile":664,"color":2,"flipX":true,"flipY":false},{"tile":501,"color":0,"flipX":false,"flipY":false},{"tile":502,"color":0,"flipX":false,"flipY":false},{"tile":503,"color":0,"flipX":false,"flipY":false},{"tile":504,"color":0,"flipX":false,"flipY":false},{"tile":647,"color":2,"flipX":true,"flipY":false},{"tile":659,"color":2,"flipX":true,"flipY":false},{"tile":667,"color":2,"flipX":true,"flipY":false},{"tile":668,"color":2,"flipX":true,"flipY":false},{"tile":667,"color":2,"flipX":true,"flipY":false},{"tile":668,"color":2,"flipX":true,"flipY":false},{"tile":667,"color":2,"flipX":true,"flipY":false},{"tile":668,"color":2,"flipX":true,"flipY":false},{"tile":667,"color":2,"flipX":true,"flipY":false},{"tile":668,"color":2,"flipX":true,"flipY":false},{"tile":667,"color":2,"flipX":true,"flipY":false},{"tile":668,"color":2,"flipX":true,"flipY":false},{"tile":667,"color":2,"flipX":true,"flipY":false},{"tile":505,"color":0,"flipX":false,"flipY":false},{"tile":506,"color":0,"flipX":false,"flipY":false},{"tile":507,"color":0,"flipX":false,"flipY":false},{"tile":647,"color":2,"flipX":true,"flipY":false},{"tile":647,"color":2,"flipX":true,"flipY":false},{"tile":651,"color":2,"flipX":true,"flipY":false},{"tile":654,"color":2,"flipX":true,"flipY":false},{"tile":654,"color":2,"flipX":true,"flipY":false},{"tile":654,"color":2,"flipX":true,"flipY":false},{"tile":654,"color":2,"flipX":true,"flipY":false},{"tile":654,"color":2,"flipX":true,"flipY":false},{"tile":654,"color":2,"flipX":true,"flipY":false},{"tile":654,"color":2,"flipX":true,"flipY":false},{"tile":654,"color":2,"flipX":true,"flipY":false},{"tile":654,"color":2,"flipX":true,"flipY":false},{"tile":654,"color":2,"flipX":true,"flipY":false},{"tile":654,"color":2,"flipX":true,"flipY":false},{"tile":642,"color":2,"flipX":true,"flipY":false},{"tile":643,"color":2,"flipX":true,"flipY":false},{"tile":647,"color":2,"flipX":true,"flipY":false},{"tile":647,"color":2,"flipX":true,"flipY":false},{"tile":647,"color":2,"flipX":true,"flipY":false},{"tile":647,"color":2,"flipX":true,"flipY":false},{"tile":647,"color":2,"flipX":true,"flipY":false},{"tile":647,"color":2,"flipX":true,"flipY":false},{"tile":647,"color":2,"flipX":true,"flipY":false},{"tile":647,"color":2,"flipX":true,"flipY":false},{"tile":647,"color":2,"flipX":true,"flipY":false},{"tile":647,"color":2,"flipX":true,"flipY":false},{"tile":647,"color":2,"flipX":true,"flipY":false},{"tile":647,"color":2,"flipX":true,"flipY":false},{"tile":647,"color":2,"flipX":true,"flipY":false},{"tile":647,"color":2,"flipX":true,"flipY":false},{"tile":647,"color":2,"flipX":true,"flipY":false},{"tile":648,"color":2,"flipX":true,"flipY":false},{"tile":647,"color":2,"flipX":true,"flipY":false},{"tile":647,"color":2,"flipX":true,"flipY":false},{"tile":647,"color":2,"flipX":true,"flipY":false},{"tile":647,"color":2,"flipX":true,"flipY":false},{"tile":647,"color":2,"flipX":true,"flipY":false},{"tile":647,"color":2,"flipX":true,"flipY":false},{"tile":647,"color":2,"flipX":true,"flipY":false},{"tile":647,"color":2,"flipX":true,"flipY":false},{"tile":647,"color":2,"flipX":true,"flipY":false},{"tile":647,"color":2,"flipX":true,"flipY":false},{"tile":647,"color":2,"flipX":true,"flipY":false},{"tile":647,"color":2,"flipX":true,"flipY":false},{"tile":647,"color":2,"flipX":true,"flipY":false},{"tile":647,"color":2,"flipX":true,"flipY":false},{"tile":647,"color":2,"flipX":true,"flipY":false},{"tile":647,"color":2,"flipX":true,"flipY":false},{"tile":431,"color":4,"flipX":true,"flipY":false},{"tile":429,"color":4,"flipX":true,"flipY":false},{"tile":429,"color":4,"flipX":true,"flipY":false},{"tile":430,"color":4,"flipX":true,"flipY":false},{"tile":431,"color":4,"flipX":true,"flipY":false},{"tile":429,"color":4,"flipX":true,"flipY":false},{"tile":429,"color":4,"flipX":true,"flipY":false},{"tile":430,"color":4,"flipX":true,"flipY":false},{"tile":431,"color":4,"flipX":true,"flipY":false},{"tile":429,"color":4,"flipX":true,"flipY":false},{"tile":429,"color":4,"flipX":true,"flipY":false},{"tile":430,"color":4,"flipX":true,"flipY":false},{"tile":431,"color":4,"flipX":true,"flipY":false},{"tile":429,"color":4,"flipX":true,"flipY":false},{"tile":429,"color":4,"flipX":true,"flipY":false},{"tile":430,"color":4,"flipX":true,"flipY":false},{"tile":434,"color":4,"flipX":true,"flipY":false},{"tile":435,"color":4,"flipX":true,"flipY":false},{"tile":432,"color":4,"flipX":true,"flipY":false},{"tile":433,"color":4,"flipX":true,"flipY":false},{"tile":434,"color":4,"flipX":true,"flipY":false},{"tile":435,"color":4,"flipX":true,"flipY":false},{"tile":432,"color":4,"flipX":true,"flipY":false},{"tile":433,"color":4,"flipX":true,"flipY":false},{"tile":434,"color":4,"flipX":true,"flipY":false},{"tile":435,"color":4,"flipX":true,"flipY":false},{"tile":432,"color":4,"flipX":true,"flipY":false},{"tile":433,"color":4,"flipX":true,"flipY":false},{"tile":434,"color":4,"flipX":true,"flipY":false},{"tile":435,"color":4,"flipX":true,"flipY":false},{"tile":432,"color":4,"flipX":true,"flipY":false},{"tile":433,"color":4,"flipX":true,"flipY":false},{"tile":438,"color":4,"flipX":true,"flipY":false},{"tile":439,"color":4,"flipX":true,"flipY":false},{"tile":436,"color":4,"flipX":true,"flipY":false},{"tile":437,"color":4,"flipX":true,"flipY":false},{"tile":438,"color":4,"flipX":true,"flipY":false},{"tile":439,"color":4,"flipX":true,"flipY":false},{"tile":436,"color":4,"flipX":true,"flipY":false},{"tile":437,"color":4,"flipX":true,"flipY":false},{"tile":438,"color":4,"flipX":true,"flipY":false},{"tile":439,"color":4,"flipX":true,"flipY":false},{"tile":436,"color":4,"flipX":true,"flipY":false},{"tile":437,"color":4,"flipX":true,"flipY":false},{"tile":438,"color":4,"flipX":true,"flipY":false},{"tile":439,"color":4,"flipX":true,"flipY":false},{"tile":436,"color":4,"flipX":true,"flipY":false},{"tile":437,"color":4,"flipX":true,"flipY":false},{"tile":431,"color":4,"flipX":true,"flipY":false},{"tile":443,"color":4,"flipX":true,"flipY":false},{"tile":440,"color":4,"flipX":true,"flipY":false},{"tile":441,"color":4,"flipX":true,"flipY":false},{"tile":442,"color":4,"flipX":true,"flipY":false},{"tile":443,"color":4,"flipX":true,"flipY":false},{"tile":440,"color":4,"flipX":true,"flipY":false},{"tile":441,"color":4,"flipX":true,"flipY":false},{"tile":442,"color":4,"flipX":true,"flipY":false},{"tile":443,"color":4,"flipX":true,"flipY":false},{"tile":440,"color":4,"flipX":true,"flipY":false},{"tile":441,"color":4,"flipX":true,"flipY":false},{"tile":442,"color":4,"flipX":true,"flipY":false},{"tile":443,"color":4,"flipX":true,"flipY":false},{"tile":440,"color":4,"flipX":true,"flipY":false},{"tile":441,"color":4,"flipX":true,"flipY":false},{"tile":431,"color":4,"flipX":true,"flipY":false},{"tile":429,"color":4,"flipX":true,"flipY":false},{"tile":448,"color":4,"flipX":true,"flipY":false},{"tile":445,"color":4,"flipX":true,"flipY":false},{"tile":446,"color":4,"flipX":true,"flipY":false},{"tile":447,"color":4,"flipX":true,"flipY":false},{"tile":444,"color":4,"flipX":true,"flipY":false},{"tile":445,"color":4,"flipX":true,"flipY":false},{"tile":446,"color":4,"flipX":true,"flipY":false},{"tile":447,"color":4,"flipX":true,"flipY":false},{"tile":444,"color":4,"flipX":true,"flipY":false},{"tile":445,"color":4,"flipX":true,"flipY":false},{"tile":446,"color":4,"flipX":true,"flipY":false},{"tile":447,"color":4,"flipX":true,"flipY":false},{"tile":444,"color":4,"flipX":true,"flipY":false},{"tile":445,"color":4,"flipX":true,"flipY":false},{"tile":431,"color":4,"flipX":true,"flipY":false},{"tile":429,"color":4,"flipX":true,"flipY":false},{"tile":429,"color":4,"flipX":true,"flipY":false},{"tile":449,"color":4,"flipX":true,"flipY":false},{"tile":450,"color":4,"flipX":true,"flipY":false},{"tile":429,"color":4,"flipX":true,"flipY":false},{"tile":429,"color":4,"flipX":true,"flipY":false},{"tile":449,"color":4,"flipX":true,"flipY":false},{"tile":450,"color":4,"flipX":true,"flipY":false},{"tile":429,"color":4,"flipX":true,"flipY":false},{"tile":429,"color":4,"flipX":true,"flipY":false},{"tile":449,"color":4,"flipX":true,"flipY":false},{"tile":450,"color":4,"flipX":true,"flipY":false},{"tile":429,"color":4,"flipX":true,"flipY":false},{"tile":429,"color":4,"flipX":true,"flipY":false},{"tile":449,"color":4,"flipX":true,"flipY":false},{"tile":431,"color":4,"flipX":true,"flipY":false},{"tile":429,"color":4,"flipX":true,"flipY":false},{"tile":429,"color":4,"flipX":true,"flipY":false},{"tile":430,"color":4,"flipX":true,"flipY":false},{"tile":431,"color":4,"flipX":true,"flipY":false},{"tile":429,"color":4,"flipX":true,"flipY":false},{"tile":429,"color":4,"flipX":true,"flipY":false},{"tile":430,"color":4,"flipX":true,"flipY":false},{"tile":431,"color":4,"flipX":true,"flipY":false},{"tile":429,"color":4,"flipX":true,"flipY":false},{"tile":429,"color":4,"flipX":true,"flipY":false},{"tile":430,"color":4,"flipX":true,"flipY":false},{"tile":431,"color":4,"flipX":true,"flipY":false},{"tile":429,"color":4,"flipX":true,"flipY":false},{"tile":429,"color":4,"flipX":true,"flipY":false},{"tile":430,"color":4,"flipX":true,"flipY":false},{"tile":434,"color":4,"flipX":true,"flipY":false},{"tile":435,"color":4,"flipX":true,"flipY":false},{"tile":432,"color":4,"flipX":true,"flipY":false},{"tile":433,"color":4,"flipX":true,"flipY":false},{"tile":434,"color":4,"flipX":true,"flipY":false},{"tile":435,"color":4,"flipX":true,"flipY":false},{"tile":432,"color":4,"flipX":true,"flipY":false},{"tile":433,"color":4,"flipX":true,"flipY":false},{"tile":434,"color":4,"flipX":true,"flipY":false},{"tile":435,"color":4,"flipX":true,"flipY":false},{"tile":432,"color":4,"flipX":true,"flipY":false},{"tile":433,"color":4,"flipX":true,"flipY":false},{"tile":434,"color":4,"flipX":true,"flipY":false},{"tile":435,"color":4,"flipX":true,"flipY":false},{"tile":432,"color":4,"flipX":true,"flipY":false},{"tile":433,"color":4,"flipX":true,"flipY":false},{"tile":438,"color":4,"flipX":true,"flipY":false},{"tile":439,"color":4,"flipX":true,"flipY":false},{"tile":436,"color":4,"flipX":true,"flipY":false},{"tile":437,"color":4,"flipX":true,"flipY":false},{"tile":438,"color":4,"flipX":true,"flipY":false},{"tile":439,"color":4,"flipX":true,"flipY":false},{"tile":436,"color":4,"flipX":true,"flipY":false},{"tile":437,"color":4,"flipX":true,"flipY":false},{"tile":438,"color":4,"flipX":true,"flipY":false},{"tile":439,"color":4,"flipX":true,"flipY":false},{"tile":436,"color":4,"flipX":true,"flipY":false},{"tile":437,"color":4,"flipX":true,"flipY":false},{"tile":438,"color":4,"flipX":true,"flipY":false},{"tile":439,"color":4,"flipX":true,"flipY":false},{"tile":436,"color":4,"flipX":true,"flipY":false},{"tile":437,"color":4,"flipX":true,"flipY":false},{"tile":431,"color":4,"flipX":true,"flipY":false},{"tile":443,"color":4,"flipX":true,"flipY":false},{"tile":440,"color":4,"flipX":true,"flipY":false},{"tile":441,"color":4,"flipX":true,"flipY":false},{"tile":442,"color":4,"flipX":true,"flipY":false},{"tile":443,"color":4,"flipX":true,"flipY":false},{"tile":440,"color":4,"flipX":true,"flipY":false},{"tile":441,"color":4,"flipX":true,"flipY":false},{"tile":442,"color":4,"flipX":true,"flipY":false},{"tile":443,"color":4,"flipX":true,"flipY":false},{"tile":440,"color":4,"flipX":true,"flipY":false},{"tile":441,"color":4,"flipX":true,"flipY":false},{"tile":442,"color":4,"flipX":true,"flipY":false},{"tile":443,"color":4,"flipX":true,"flipY":false},{"tile":440,"color":4,"flipX":true,"flipY":false},{"tile":441,"color":4,"flipX":true,"flipY":false},{"tile":431,"color":4,"flipX":true,"flipY":false},{"tile":429,"color":4,"flipX":true,"flipY":false},{"tile":448,"color":4,"flipX":true,"flipY":false},{"tile":445,"color":4,"flipX":true,"flipY":false},{"tile":446,"color":4,"flipX":true,"flipY":false},{"tile":447,"color":4,"flipX":true,"flipY":false},{"tile":444,"color":4,"flipX":true,"flipY":false},{"tile":445,"color":4,"flipX":true,"flipY":false},{"tile":446,"color":4,"flipX":true,"flipY":false},{"tile":447,"color":4,"flipX":true,"flipY":false},{"tile":444,"color":4,"flipX":true,"flipY":false},{"tile":445,"color":4,"flipX":true,"flipY":false},{"tile":446,"color":4,"flipX":true,"flipY":false},{"tile":447,"color":4,"flipX":true,"flipY":false},{"tile":444,"color":4,"flipX":true,"flipY":false},{"tile":445,"color":4,"flipX":true,"flipY":false},{"tile":431,"color":4,"flipX":true,"flipY":false},{"tile":429,"color":4,"flipX":true,"flipY":false},{"tile":429,"color":4,"flipX":true,"flipY":false},{"tile":449,"color":4,"flipX":true,"flipY":false},{"tile":450,"color":4,"flipX":true,"flipY":false},{"tile":429,"color":4,"flipX":true,"flipY":false},{"tile":429,"color":4,"flipX":true,"flipY":false},{"tile":449,"color":4,"flipX":true,"flipY":false},{"tile":450,"color":4,"flipX":true,"flipY":false},{"tile":429,"color":4,"flipX":true,"flipY":false},{"tile":429,"color":4,"flipX":true,"flipY":false},{"tile":449,"color":4,"flipX":true,"flipY":false},{"tile":450,"color":4,"flipX":true,"flipY":false},{"tile":429,"color":4,"flipX":true,"flipY":false},{"tile":429,"color":4,"flipX":true,"flipY":false},{"tile":449,"color":4,"flipX":true,"flipY":false},{"tile":431,"color":4,"flipX":true,"flipY":false},{"tile":429,"color":4,"flipX":true,"flipY":false},{"tile":429,"color":4,"flipX":true,"flipY":false},{"tile":430,"color":4,"flipX":true,"flipY":false},{"tile":431,"color":4,"flipX":true,"flipY":false},{"tile":429,"color":4,"flipX":true,"flipY":false},{"tile":429,"color":4,"flipX":true,"flipY":false},{"tile":452,"color":4,"flipX":true,"flipY":false},{"tile":453,"color":4,"flipX":true,"flipY":false},{"tile":429,"color":4,"flipX":true,"flipY":false},{"tile":429,"color":4,"flipX":true,"flipY":false},{"tile":452,"color":4,"flipX":true,"flipY":false},{"tile":453,"color":4,"flipX":true,"flipY":false},{"tile":429,"color":4,"flipX":true,"flipY":false},{"tile":429,"color":4,"flipX":true,"flipY":false},{"tile":452,"color":4,"flipX":true,"flipY":false},{"tile":434,"color":4,"flipX":true,"flipY":false},{"tile":435,"color":4,"flipX":true,"flipY":false},{"tile":432,"color":4,"flipX":true,"flipY":false},{"tile":430,"color":4,"flipX":true,"flipY":false},{"tile":683,"color":2,"flipX":true,"flipY":false},{"tile":684,"color":2,"flipX":true,"flipY":false},{"tile":684,"color":2,"flipX":true,"flipY":false},{"tile":685,"color":2,"flipX":true,"flipY":false},{"tile":683,"color":2,"flipX":true,"flipY":false},{"tile":684,"color":2,"flipX":true,"flipY":false},{"tile":684,"color":2,"flipX":true,"flipY":false},{"tile":685,"color":2,"flipX":true,"flipY":false},{"tile":683,"color":2,"flipX":true,"flipY":false},{"tile":684,"color":2,"flipX":true,"flipY":false},{"tile":684,"color":2,"flipX":true,"flipY":false},{"tile":685,"color":2,"flipX":true,"flipY":false},{"tile":438,"color":4,"flipX":true,"flipY":false},{"tile":439,"color":4,"flipX":true,"flipY":false},{"tile":436,"color":4,"flipX":true,"flipY":false},{"tile":430,"color":4,"flipX":true,"flipY":false},{"tile":686,"color":2,"flipX":true,"flipY":false},{"tile":687,"color":2,"flipX":true,"flipY":false},{"tile":687,"color":2,"flipX":true,"flipY":false},{"tile":688,"color":2,"flipX":true,"flipY":false},{"tile":686,"color":2,"flipX":true,"flipY":false},{"tile":687,"color":2,"flipX":true,"flipY":false},{"tile":687,"color":2,"flipX":true,"flipY":false},{"tile":688,"color":2,"flipX":true,"flipY":false},{"tile":686,"color":2,"flipX":true,"flipY":false},{"tile":687,"color":2,"flipX":true,"flipY":false},{"tile":687,"color":2,"flipX":true,"flipY":false},{"tile":688,"color":2,"flipX":true,"flipY":false},{"tile":453,"color":4,"flipX":true,"flipY":false},{"tile":443,"color":4,"flipX":true,"flipY":false},{"tile":440,"color":4,"flipX":true,"flipY":false},{"tile":452,"color":4,"flipX":true,"flipY":false},{"tile":686,"color":2,"flipX":true,"flipY":false},{"tile":687,"color":2,"flipX":true,"flipY":false},{"tile":687,"color":2,"flipX":true,"flipY":false},{"tile":688,"color":2,"flipX":true,"flipY":false},{"tile":686,"color":2,"flipX":true,"flipY":false},{"tile":687,"color":2,"flipX":true,"flipY":false},{"tile":687,"color":2,"flipX":true,"flipY":false},{"tile":688,"color":2,"flipX":true,"flipY":false},{"tile":686,"color":2,"flipX":true,"flipY":false},{"tile":687,"color":2,"flipX":true,"flipY":false},{"tile":687,"color":2,"flipX":true,"flipY":false},{"tile":688,"color":2,"flipX":true,"flipY":false},{"tile":660,"color":2,"flipX":true,"flipY":false},{"tile":561,"color":2,"flipX":false,"flipY":false},{"tile":562,"color":2,"flipX":false,"flipY":false},{"tile":563,"color":2,"flipX":false,"flipY":false},{"tile":564,"color":2,"flipX":false,"flipY":false},{"tile":544,"color":2,"flipX":false,"flipY":false},{"tile":551,"color":2,"flipX":false,"flipY":false},{"tile":552,"color":2,"flipX":false,"flipY":false},{"tile":554,"color":2,"flipX":false,"flipY":false},{"tile":563,"color":2,"flipX":false,"flipY":false},{"tile":564,"color":2,"flipX":false,"flipY":false},{"tile":544,"color":2,"flipX":false,"flipY":false},{"tile":551,"color":2,"flipX":false,"flipY":false},{"tile":552,"color":2,"flipX":false,"flipY":false},{"tile":554,"color":2,"flipX":false,"flipY":false},{"tile":544,"color":2,"flipX":false,"flipY":false},{"tile":660,"color":2,"flipX":true,"flipY":false},{"tile":566,"color":2,"flipX":false,"flipY":false},{"tile":567,"color":2,"flipX":false,"flipY":false},{"tile":568,"color":2,"flipX":false,"flipY":false},{"tile":569,"color":2,"flipX":false,"flipY":false},{"tile":570,"color":2,"flipX":false,"flipY":false},{"tile":540,"color":2,"flipX":false,"flipY":false},{"tile":541,"color":2,"flipX":false,"flipY":false},{"tile":557,"color":2,"flipX":false,"flipY":false},{"tile":571,"color":2,"flipX":false,"flipY":false},{"tile":572,"color":2,"flipX":false,"flipY":false},{"tile":576,"color":2,"flipX":false,"flipY":false},{"tile":540,"color":2,"flipX":false,"flipY":false},{"tile":624,"color":4,"flipX":false,"flipY":false},{"tile":596,"color":4,"flipX":false,"flipY":false},{"tile":596,"color":4,"flipX":false,"flipY":false},{"tile":660,"color":2,"flipX":true,"flipY":false},{"tile":566,"color":2,"flipX":false,"flipY":false},{"tile":567,"color":2,"flipX":false,"flipY":false},{"tile":573,"color":2,"flipX":false,"flipY":false},{"tile":574,"color":2,"flipX":false,"flipY":false},{"tile":575,"color":2,"flipX":false,"flipY":false},{"tile":545,"color":2,"flipX":false,"flipY":false},{"tile":546,"color":2,"flipX":false,"flipY":false},{"tile":560,"color":2,"flipX":false,"flipY":false},{"tile":573,"color":2,"flipX":false,"flipY":false},{"tile":574,"color":2,"flipX":false,"flipY":false},{"tile":582,"color":2,"flipX":false,"flipY":false},{"tile":545,"color":2,"flipX":false,"flipY":false},{"tile":628,"color":4,"flipX":false,"flipY":false},{"tile":600,"color":4,"flipX":false,"flipY":false},{"tile":601,"color":4,"flipX":false,"flipY":false},{"tile":662,"color":2,"flipX":true,"flipY":false},{"tile":577,"color":2,"flipX":false,"flipY":false},{"tile":578,"color":2,"flipX":false,"flipY":false},{"tile":579,"color":2,"flipX":false,"flipY":false},{"tile":580,"color":2,"flipX":false,"flipY":false},{"tile":581,"color":2,"flipX":false,"flipY":false},{"tile":590,"color":2,"flipX":false,"flipY":false},{"tile":591,"color":2,"flipX":false,"flipY":false},{"tile":565,"color":2,"flipX":false,"flipY":false},{"tile":579,"color":2,"flipX":false,"flipY":false},{"tile":580,"color":2,"flipX":false,"flipY":false},{"tile":554,"color":2,"flipX":false,"flipY":false},{"tile":590,"color":2,"flipX":false,"flipY":false},{"tile":629,"color":4,"flipX":false,"flipY":false},{"tile":603,"color":4,"flipX":false,"flipY":false},{"tile":604,"color":4,"flipX":false,"flipY":false},{"tile":674,"color":2,"flipX":true,"flipY":false},{"tile":583,"color":2,"flipX":false,"flipY":false},{"tile":584,"color":2,"flipX":false,"flipY":false},{"tile":585,"color":2,"flipX":false,"flipY":false},{"tile":586,"color":2,"flipX":false,"flipY":false},{"tile":587,"color":2,"flipX":false,"flipY":false},{"tile":594,"color":2,"flipX":false,"flipY":false},{"tile":595,"color":2,"flipX":false,"flipY":false},{"tile":630,"color":4,"flipX":false,"flipY":false},{"tile":631,"color":4,"flipX":false,"flipY":false},{"tile":631,"color":4,"flipX":false,"flipY":false},{"tile":631,"color":4,"flipX":false,"flipY":false},{"tile":631,"color":4,"flipX":false,"flipY":false},{"tile":632,"color":4,"flipX":false,"flipY":false},{"tile":606,"color":4,"flipX":false,"flipY":false},{"tile":607,"color":4,"flipX":false,"flipY":false},{"tile":678,"color":2,"flipX":true,"flipY":false},{"tile":588,"color":2,"flipX":false,"flipY":false},{"tile":589,"color":2,"flipX":false,"flipY":false},{"tile":518,"color":0,"flipX":false,"flipY":false},{"tile":519,"color":0,"flipX":false,"flipY":false},{"tile":520,"color":0,"flipX":false,"flipY":false},{"tile":518,"color":0,"flipX":false,"flipY":false},{"tile":519,"color":0,"flipX":false,"flipY":false},{"tile":633,"color":4,"flipX":false,"flipY":false},{"tile":634,"color":4,"flipX":false,"flipY":false},{"tile":635,"color":4,"flipX":false,"flipY":false},{"tile":635,"color":4,"flipX":false,"flipY":false},{"tile":635,"color":4,"flipX":false,"flipY":false},{"tile":636,"color":4,"flipX":false,"flipY":false},{"tile":609,"color":4,"flipX":false,"flipY":false},{"tile":610,"color":4,"flipX":false,"flipY":false},{"tile":678,"color":2,"flipX":true,"flipY":false},{"tile":592,"color":2,"flipX":false,"flipY":false},{"tile":593,"color":2,"flipX":false,"flipY":false},{"tile":521,"color":0,"flipX":false,"flipY":false},{"tile":522,"color":0,"flipX":false,"flipY":false},{"tile":523,"color":0,"flipX":false,"flipY":false},{"tile":524,"color":0,"flipX":false,"flipY":false},{"tile":522,"color":0,"flipX":false,"flipY":false},{"tile":637,"color":4,"flipX":false,"flipY":false},{"tile":638,"color":4,"flipX":false,"flipY":false},{"tile":639,"color":4,"flipX":false,"flipY":false},{"tile":639,"color":4,"flipX":false,"flipY":false},{"tile":639,"color":4,"flipX":false,"flipY":false},{"tile":640,"color":4,"flipX":false,"flipY":false},{"tile":613,"color":4,"flipX":false,"flipY":false},{"tile":614,"color":4,"flipX":false,"flipY":false},{"tile":678,"color":2,"flipX":true,"flipY":false},{"tile":592,"color":2,"flipX":false,"flipY":false},{"tile":593,"color":2,"flipX":false,"flipY":false},{"tile":525,"color":0,"flipX":false,"flipY":false},{"tile":521,"color":0,"flipX":false,"flipY":false},{"tile":522,"color":0,"flipX":false,"flipY":false},{"tile":523,"color":0,"flipX":false,"flipY":false},{"tile":524,"color":0,"flipX":false,"flipY":false},{"tile":522,"color":0,"flipX":false,"flipY":false},{"tile":523,"color":0,"flipX":false,"flipY":false},{"tile":524,"color":0,"flipX":false,"flipY":false},{"tile":522,"color":0,"flipX":false,"flipY":false},{"tile":523,"color":0,"flipX":false,"flipY":false},{"tile":641,"color":4,"flipX":false,"flipY":false},{"tile":619,"color":4,"flipX":false,"flipY":false},{"tile":620,"color":4,"flipX":false,"flipY":false},{"tile":474,"color":0,"flipX":false,"flipY":false},{"tile":474,"color":0,"flipX":false,"flipY":false},{"tile":459,"color":0,"flipX":false,"flipY":false},{"tile":526,"color":0,"flipX":false,"flipY":false},{"tile":525,"color":0,"flipX":false,"flipY":false},{"tile":521,"color":0,"flipX":false,"flipY":false},{"tile":522,"color":0,"flipX":false,"flipY":false},{"tile":523,"color":0,"flipX":false,"flipY":false},{"tile":524,"color":0,"flipX":false,"flipY":false},{"tile":522,"color":0,"flipX":false,"flipY":false},{"tile":523,"color":0,"flipX":false,"flipY":false},{"tile":524,"color":0,"flipX":false,"flipY":false},{"tile":522,"color":0,"flipX":false,"flipY":false},{"tile":523,"color":0,"flipX":false,"flipY":false},{"tile":524,"color":0,"flipX":false,"flipY":false},{"tile":522,"color":0,"flipX":false,"flipY":false},{"tile":479,"color":0,"flipX":false,"flipY":false},{"tile":479,"color":0,"flipX":false,"flipY":false},{"tile":479,"color":0,"flipX":false,"flipY":false},{"tile":462,"color":0,"flipX":false,"flipY":false},{"tile":526,"color":0,"flipX":false,"flipY":false},{"tile":525,"color":0,"flipX":false,"flipY":false},{"tile":512,"color":0,"flipX":false,"flipY":false},{"tile":514,"color":0,"flipX":false,"flipY":false},{"tile":513,"color":0,"flipX":false,"flipY":false},{"tile":515,"color":0,"flipX":false,"flipY":false},{"tile":516,"color":0,"flipX":false,"flipY":false},{"tile":517,"color":0,"flipX":false,"flipY":false},{"tile":512,"color":0,"flipX":false,"flipY":false},{"tile":513,"color":0,"flipX":false,"flipY":false},{"tile":514,"color":0,"flipX":false,"flipY":false},{"tile":515,"color":0,"flipX":false,"flipY":false},{"tile":500,"color":0,"flipX":false,"flipY":false},{"tile":499,"color":0,"flipX":false,"flipY":false},{"tile":500,"color":0,"flipX":false,"flipY":false},{"tile":465,"color":0,"flipX":false,"flipY":false},{"tile":527,"color":0,"flipX":false,"flipY":false},{"tile":526,"color":0,"flipX":false,"flipY":false},{"tile":514,"color":0,"flipX":false,"flipY":false},{"tile":512,"color":0,"flipX":false,"flipY":false},{"tile":513,"color":0,"flipX":false,"flipY":false},{"tile":514,"color":0,"flipX":false,"flipY":false},{"tile":515,"color":0,"flipX":false,"flipY":false},{"tile":516,"color":0,"flipX":false,"flipY":false},{"tile":517,"color":0,"flipX":false,"flipY":false},{"tile":512,"color":0,"flipX":false,"flipY":false},{"tile":514,"color":0,"flipX":false,"flipY":false},{"tile":515,"color":0,"flipX":false,"flipY":false},{"tile":468,"color":0,"flipX":false,"flipY":false},{"tile":504,"color":0,"flipX":false,"flipY":false},{"tile":468,"color":0,"flipX":false,"flipY":false},{"tile":469,"color":0,"flipX":false,"flipY":false},{"tile":525,"color":0,"flipX":false,"flipY":false},{"tile":527,"color":0,"flipX":false,"flipY":false},{"tile":512,"color":0,"flipX":false,"flipY":false},{"tile":513,"color":0,"flipX":false,"flipY":false},{"tile":516,"color":0,"flipX":false,"flipY":false},{"tile":517,"color":0,"flipX":false,"flipY":false},{"tile":512,"color":0,"flipX":false,"flipY":false},{"tile":513,"color":0,"flipX":false,"flipY":false},{"tile":514,"color":0,"flipX":false,"flipY":false},{"tile":515,"color":0,"flipX":false,"flipY":false},{"tile":534,"color":0,"flipX":false,"flipY":false},{"tile":535,"color":0,"flipX":false,"flipY":false},{"tile":508,"color":0,"flipX":false,"flipY":false},{"tile":509,"color":0,"flipX":false,"flipY":false},{"tile":508,"color":0,"flipX":false,"flipY":false},{"tile":507,"color":0,"flipX":false,"flipY":false},{"tile":526,"color":0,"flipX":false,"flipY":false},{"tile":525,"color":0,"flipX":false,"flipY":false},{"tile":513,"color":0,"flipX":false,"flipY":false},{"tile":514,"color":0,"flipX":false,"flipY":false},{"tile":512,"color":0,"flipX":false,"flipY":false},{"tile":513,"color":0,"flipX":false,"flipY":false},{"tile":517,"color":0,"flipX":false,"flipY":false},{"tile":514,"color":0,"flipX":false,"flipY":false},{"tile":515,"color":0,"flipX":false,"flipY":false},{"tile":516,"color":0,"flipX":false,"flipY":false},{"tile":513,"color":0,"flipX":false,"flipY":false},{"tile":512,"color":0,"flipX":false,"flipY":false},{"tile":644,"color":2,"flipX":true,"flipY":false},{"tile":645,"color":2,"flipX":true,"flipY":false},{"tile":645,"color":2,"flipX":true,"flipY":false},{"tile":645,"color":2,"flipX":true,"flipY":false},{"tile":531,"color":0,"flipX":false,"flipY":false},{"tile":526,"color":0,"flipX":false,"flipY":false},{"tile":515,"color":0,"flipX":false,"flipY":false},{"tile":515,"color":0,"flipX":false,"flipY":false},{"tile":514,"color":0,"flipX":false,"flipY":false},{"tile":512,"color":0,"flipX":false,"flipY":false},{"tile":532,"color":0,"flipX":false,"flipY":false},{"tile":533,"color":0,"flipX":false,"flipY":false},{"tile":512,"color":0,"flipX":false,"flipY":false},{"tile":513,"color":0,"flipX":false,"flipY":false},{"tile":514,"color":0,"flipX":false,"flipY":false},{"tile":515,"color":0,"flipX":false,"flipY":false},{"tile":649,"color":2,"flipX":true,"flipY":false},{"tile":649,"color":2,"flipX":true,"flipY":false},{"tile":649,"color":2,"flipX":true,"flipY":false},{"tile":649,"color":2,"flipX":true,"flipY":false},{"tile":649,"color":2,"flipX":true,"flipY":false},{"tile":531,"color":0,"flipX":false,"flipY":false},{"tile":516,"color":0,"flipX":false,"flipY":false},{"tile":512,"color":0,"flipX":false,"flipY":false},{"tile":515,"color":0,"flipX":false,"flipY":false},{"tile":512,"color":0,"flipX":false,"flipY":false},{"tile":513,"color":0,"flipX":false,"flipY":false},{"tile":514,"color":0,"flipX":false,"flipY":false},{"tile":515,"color":0,"flipX":false,"flipY":false},{"tile":516,"color":0,"flipX":false,"flipY":false},{"tile":517,"color":0,"flipX":false,"flipY":false},{"tile":512,"color":0,"flipX":false,"flipY":false},{"tile":652,"color":2,"flipX":true,"flipY":false},{"tile":653,"color":2,"flipX":true,"flipY":false},{"tile":653,"color":2,"flipX":true,"flipY":false},{"tile":653,"color":2,"flipX":true,"flipY":false},{"tile":653,"color":2,"flipX":true,"flipY":false},{"tile":653,"color":2,"flipX":true,"flipY":false},{"tile":517,"color":0,"flipX":false,"flipY":false},{"tile":513,"color":0,"flipX":false,"flipY":false},{"tile":512,"color":0,"flipX":false,"flipY":false},{"tile":513,"color":0,"flipX":false,"flipY":false},{"tile":514,"color":0,"flipX":false,"flipY":false},{"tile":515,"color":0,"flipX":false,"flipY":false},{"tile":512,"color":0,"flipX":false,"flipY":false},{"tile":513,"color":0,"flipX":false,"flipY":false},{"tile":514,"color":0,"flipX":false,"flipY":false},{"tile":515,"color":0,"flipX":false,"flipY":false},{"tile":431,"color":4,"flipX":true,"flipY":false},{"tile":429,"color":4,"flipX":true,"flipY":false},{"tile":429,"color":4,"flipX":true,"flipY":false},{"tile":430,"color":4,"flipX":true,"flipY":false},{"tile":431,"color":4,"flipX":true,"flipY":false},{"tile":429,"color":4,"flipX":true,"flipY":false},{"tile":429,"color":4,"flipX":true,"flipY":false},{"tile":430,"color":4,"flipX":true,"flipY":false},{"tile":431,"color":4,"flipX":true,"flipY":false},{"tile":429,"color":4,"flipX":true,"flipY":false},{"tile":429,"color":4,"flipX":true,"flipY":false},{"tile":430,"color":4,"flipX":true,"flipY":false},{"tile":431,"color":4,"flipX":true,"flipY":false},{"tile":429,"color":4,"flipX":true,"flipY":false},{"tile":429,"color":4,"flipX":true,"flipY":false},{"tile":430,"color":4,"flipX":true,"flipY":false},{"tile":434,"color":4,"flipX":true,"flipY":false},{"tile":435,"color":4,"flipX":true,"flipY":false},{"tile":432,"color":4,"flipX":true,"flipY":false},{"tile":433,"color":4,"flipX":true,"flipY":false},{"tile":434,"color":4,"flipX":true,"flipY":false},{"tile":435,"color":4,"flipX":true,"flipY":false},{"tile":432,"color":4,"flipX":true,"flipY":false},{"tile":433,"color":4,"flipX":true,"flipY":false},{"tile":434,"color":4,"flipX":true,"flipY":false},{"tile":435,"color":4,"flipX":true,"flipY":false},{"tile":432,"color":4,"flipX":true,"flipY":false},{"tile":433,"color":4,"flipX":true,"flipY":false},{"tile":434,"color":4,"flipX":true,"flipY":false},{"tile":435,"color":4,"flipX":true,"flipY":false},{"tile":432,"color":4,"flipX":true,"flipY":false},{"tile":433,"color":4,"flipX":true,"flipY":false},{"tile":438,"color":4,"flipX":true,"flipY":false},{"tile":439,"color":4,"flipX":true,"flipY":false},{"tile":436,"color":4,"flipX":true,"flipY":false},{"tile":437,"color":4,"flipX":true,"flipY":false},{"tile":438,"color":4,"flipX":true,"flipY":false},{"tile":439,"color":4,"flipX":true,"flipY":false},{"tile":436,"color":4,"flipX":true,"flipY":false},{"tile":437,"color":4,"flipX":true,"flipY":false},{"tile":438,"color":4,"flipX":true,"flipY":false},{"tile":439,"color":4,"flipX":true,"flipY":false},{"tile":436,"color":4,"flipX":true,"flipY":false},{"tile":437,"color":4,"flipX":true,"flipY":false},{"tile":438,"color":4,"flipX":true,"flipY":false},{"tile":439,"color":4,"flipX":true,"flipY":false},{"tile":436,"color":4,"flipX":true,"flipY":false},{"tile":437,"color":4,"flipX":true,"flipY":false},{"tile":442,"color":4,"flipX":true,"flipY":false},{"tile":443,"color":4,"flipX":true,"flipY":false},{"tile":440,"color":4,"flipX":true,"flipY":false},{"tile":441,"color":4,"flipX":true,"flipY":false},{"tile":442,"color":4,"flipX":true,"flipY":false},{"tile":443,"color":4,"flipX":true,"flipY":false},{"tile":440,"color":4,"flipX":true,"flipY":false},{"tile":441,"color":4,"flipX":true,"flipY":false},{"tile":442,"color":4,"flipX":true,"flipY":false},{"tile":443,"color":4,"flipX":true,"flipY":false},{"tile":440,"color":4,"flipX":true,"flipY":false},{"tile":441,"color":4,"flipX":true,"flipY":false},{"tile":442,"color":4,"flipX":true,"flipY":false},{"tile":443,"color":4,"flipX":true,"flipY":false},{"tile":440,"color":4,"flipX":true,"flipY":false},{"tile":441,"color":4,"flipX":true,"flipY":false},{"tile":446,"color":4,"flipX":true,"flipY":false},{"tile":447,"color":4,"flipX":true,"flipY":false},{"tile":444,"color":4,"flipX":true,"flipY":false},{"tile":445,"color":4,"flipX":true,"flipY":false},{"tile":446,"color":4,"flipX":true,"flipY":false},{"tile":447,"color":4,"flipX":true,"flipY":false},{"tile":444,"color":4,"flipX":true,"flipY":false},{"tile":445,"color":4,"flipX":true,"flipY":false},{"tile":446,"color":4,"flipX":true,"flipY":false},{"tile":447,"color":4,"flipX":true,"flipY":false},{"tile":444,"color":4,"flipX":true,"flipY":false},{"tile":445,"color":4,"flipX":true,"flipY":false},{"tile":446,"color":4,"flipX":true,"flipY":false},{"tile":447,"color":4,"flipX":true,"flipY":false},{"tile":444,"color":4,"flipX":true,"flipY":false},{"tile":445,"color":4,"flipX":true,"flipY":false},{"tile":450,"color":4,"flipX":true,"flipY":false},{"tile":429,"color":4,"flipX":true,"flipY":false},{"tile":429,"color":4,"flipX":true,"flipY":false},{"tile":449,"color":4,"flipX":true,"flipY":false},{"tile":450,"color":4,"flipX":true,"flipY":false},{"tile":429,"color":4,"flipX":true,"flipY":false},{"tile":429,"color":4,"flipX":true,"flipY":false},{"tile":449,"color":4,"flipX":true,"flipY":false},{"tile":450,"color":4,"flipX":true,"flipY":false},{"tile":429,"color":4,"flipX":true,"flipY":false},{"tile":429,"color":4,"flipX":true,"flipY":false},{"tile":449,"color":4,"flipX":true,"flipY":false},{"tile":450,"color":4,"flipX":true,"flipY":false},{"tile":429,"color":4,"flipX":true,"flipY":false},{"tile":429,"color":4,"flipX":true,"flipY":false},{"tile":449,"color":4,"flipX":true,"flipY":false},{"tile":431,"color":4,"flipX":true,"flipY":false},{"tile":429,"color":4,"flipX":true,"flipY":false},{"tile":429,"color":4,"flipX":true,"flipY":false},{"tile":430,"color":4,"flipX":true,"flipY":false},{"tile":431,"color":4,"flipX":true,"flipY":false},{"tile":429,"color":4,"flipX":true,"flipY":false},{"tile":429,"color":4,"flipX":true,"flipY":false},{"tile":430,"color":4,"flipX":true,"flipY":false},{"tile":431,"color":4,"flipX":true,"flipY":false},{"tile":429,"color":4,"flipX":true,"flipY":false},{"tile":429,"color":4,"flipX":true,"flipY":false},{"tile":430,"color":4,"flipX":true,"flipY":false},{"tile":431,"color":4,"flipX":true,"flipY":false},{"tile":429,"color":4,"flipX":true,"flipY":false},{"tile":429,"color":4,"flipX":true,"flipY":false},{"tile":430,"color":4,"flipX":true,"flipY":false},{"tile":434,"color":4,"flipX":true,"flipY":false},{"tile":435,"color":4,"flipX":true,"flipY":false},{"tile":432,"color":4,"flipX":true,"flipY":false},{"tile":433,"color":4,"flipX":true,"flipY":false},{"tile":434,"color":4,"flipX":true,"flipY":false},{"tile":435,"color":4,"flipX":true,"flipY":false},{"tile":432,"color":4,"flipX":true,"flipY":false},{"tile":433,"color":4,"flipX":true,"flipY":false},{"tile":434,"color":4,"flipX":true,"flipY":false},{"tile":435,"color":4,"flipX":true,"flipY":false},{"tile":432,"color":4,"flipX":true,"flipY":false},{"tile":433,"color":4,"flipX":true,"flipY":false},{"tile":434,"color":4,"flipX":true,"flipY":false},{"tile":435,"color":4,"flipX":true,"flipY":false},{"tile":432,"color":4,"flipX":true,"flipY":false},{"tile":433,"color":4,"flipX":true,"flipY":false},{"tile":438,"color":4,"flipX":true,"flipY":false},{"tile":439,"color":4,"flipX":true,"flipY":false},{"tile":436,"color":4,"flipX":true,"flipY":false},{"tile":437,"color":4,"flipX":true,"flipY":false},{"tile":438,"color":4,"flipX":true,"flipY":false},{"tile":439,"color":4,"flipX":true,"flipY":false},{"tile":436,"color":4,"flipX":true,"flipY":false},{"tile":437,"color":4,"flipX":true,"flipY":false},{"tile":438,"color":4,"flipX":true,"flipY":false},{"tile":439,"color":4,"flipX":true,"flipY":false},{"tile":436,"color":4,"flipX":true,"flipY":false},{"tile":437,"color":4,"flipX":true,"flipY":false},{"tile":438,"color":4,"flipX":true,"flipY":false},{"tile":439,"color":4,"flipX":true,"flipY":false},{"tile":436,"color":4,"flipX":true,"flipY":false},{"tile":437,"color":4,"flipX":true,"flipY":false},{"tile":442,"color":4,"flipX":true,"flipY":false},{"tile":443,"color":4,"flipX":true,"flipY":false},{"tile":440,"color":4,"flipX":true,"flipY":false},{"tile":441,"color":4,"flipX":true,"flipY":false},{"tile":442,"color":4,"flipX":true,"flipY":false},{"tile":443,"color":4,"flipX":true,"flipY":false},{"tile":440,"color":4,"flipX":true,"flipY":false},{"tile":441,"color":4,"flipX":true,"flipY":false},{"tile":442,"color":4,"flipX":true,"flipY":false},{"tile":443,"color":4,"flipX":true,"flipY":false},{"tile":440,"color":4,"flipX":true,"flipY":false},{"tile":441,"color":4,"flipX":true,"flipY":false},{"tile":442,"color":4,"flipX":true,"flipY":false},{"tile":443,"color":4,"flipX":true,"flipY":false},{"tile":440,"color":4,"flipX":true,"flipY":false},{"tile":441,"color":4,"flipX":true,"flipY":false},{"tile":446,"color":4,"flipX":true,"flipY":false},{"tile":447,"color":4,"flipX":true,"flipY":false},{"tile":444,"color":4,"flipX":true,"flipY":false},{"tile":445,"color":4,"flipX":true,"flipY":false},{"tile":446,"color":4,"flipX":true,"flipY":false},{"tile":447,"color":4,"flipX":true,"flipY":false},{"tile":444,"color":4,"flipX":true,"flipY":false},{"tile":445,"color":4,"flipX":true,"flipY":false},{"tile":446,"color":4,"flipX":true,"flipY":false},{"tile":447,"color":4,"flipX":true,"flipY":false},{"tile":444,"color":4,"flipX":true,"flipY":false},{"tile":445,"color":4,"flipX":true,"flipY":false},{"tile":446,"color":4,"flipX":true,"flipY":false},{"tile":447,"color":4,"flipX":true,"flipY":false},{"tile":444,"color":4,"flipX":true,"flipY":false},{"tile":445,"color":4,"flipX":true,"flipY":false},{"tile":450,"color":4,"flipX":true,"flipY":false},{"tile":429,"color":4,"flipX":true,"flipY":false},{"tile":429,"color":4,"flipX":true,"flipY":false},{"tile":449,"color":4,"flipX":true,"flipY":false},{"tile":450,"color":4,"flipX":true,"flipY":false},{"tile":429,"color":4,"flipX":true,"flipY":false},{"tile":429,"color":4,"flipX":true,"flipY":false},{"tile":449,"color":4,"flipX":true,"flipY":false},{"tile":450,"color":4,"flipX":true,"flipY":false},{"tile":429,"color":4,"flipX":true,"flipY":false},{"tile":429,"color":4,"flipX":true,"flipY":false},{"tile":449,"color":4,"flipX":true,"flipY":false},{"tile":450,"color":4,"flipX":true,"flipY":false},{"tile":429,"color":4,"flipX":true,"flipY":false},{"tile":429,"color":4,"flipX":true,"flipY":false},{"tile":449,"color":4,"flipX":true,"flipY":false},{"tile":549,"color":2,"flipX":false,"flipY":false},{"tile":550,"color":2,"flipX":false,"flipY":false},{"tile":550,"color":2,"flipX":false,"flipY":false},{"tile":550,"color":2,"flipX":false,"flipY":false},{"tile":550,"color":2,"flipX":false,"flipY":false},{"tile":536,"color":2,"flipX":false,"flipY":false},{"tile":537,"color":2,"flipX":false,"flipY":false},{"tile":538,"color":2,"flipX":false,"flipY":false},{"tile":550,"color":2,"flipX":false,"flipY":false},{"tile":550,"color":2,"flipX":false,"flipY":false},{"tile":550,"color":2,"flipX":false,"flipY":false},{"tile":536,"color":2,"flipX":false,"flipY":false},{"tile":537,"color":2,"flipX":false,"flipY":false},{"tile":538,"color":2,"flipX":false,"flipY":false},{"tile":550,"color":2,"flipX":false,"flipY":false},{"tile":550,"color":2,"flipX":false,"flipY":false},{"tile":658,"color":2,"flipX":true,"flipY":false},{"tile":553,"color":2,"flipX":false,"flipY":false},{"tile":553,"color":2,"flipX":false,"flipY":false},{"tile":553,"color":2,"flipX":false,"flipY":false},{"tile":553,"color":2,"flipX":false,"flipY":false},{"tile":539,"color":2,"flipX":false,"flipY":false},{"tile":540,"color":2,"flipX":false,"flipY":false},{"tile":541,"color":2,"flipX":false,"flipY":false},{"tile":542,"color":2,"flipX":false,"flipY":false},{"tile":542,"color":2,"flipX":false,"flipY":false},{"tile":542,"color":2,"flipX":false,"flipY":false},{"tile":542,"color":2,"flipX":false,"flipY":false},{"tile":540,"color":2,"flipX":false,"flipY":false},{"tile":541,"color":2,"flipX":false,"flipY":false},{"tile":542,"color":2,"flipX":false,"flipY":false},{"tile":543,"color":2,"flipX":false,"flipY":false},{"tile":660,"color":2,"flipX":true,"flipY":false},{"tile":554,"color":2,"flipX":false,"flipY":false},{"tile":544,"color":2,"flipX":false,"flipY":false},{"tile":555,"color":2,"flipX":false,"flipY":false},{"tile":556,"color":2,"flipX":false,"flipY":false},{"tile":547,"color":2,"flipX":false,"flipY":false},{"tile":545,"color":2,"flipX":false,"flipY":false},{"tile":546,"color":2,"flipX":false,"flipY":false},{"tile":547,"color":2,"flipX":false,"flipY":false},{"tile":555,"color":2,"flipX":false,"flipY":false},{"tile":556,"color":2,"flipX":false,"flipY":false},{"tile":547,"color":2,"flipX":false,"flipY":false},{"tile":545,"color":2,"flipX":false,"flipY":false},{"tile":546,"color":2,"flipX":false,"flipY":false},{"tile":547,"color":2,"flipX":false,"flipY":false},{"tile":548,"color":2,"flipX":false,"flipY":false},{"tile":660,"color":2,"flipX":true,"flipY":false},{"tile":554,"color":2,"flipX":false,"flipY":false},{"tile":544,"color":2,"flipX":false,"flipY":false},{"tile":558,"color":2,"flipX":false,"flipY":false},{"tile":559,"color":2,"flipX":false,"flipY":false},{"tile":544,"color":2,"flipX":false,"flipY":false},{"tile":551,"color":2,"flipX":false,"flipY":false},{"tile":552,"color":2,"flipX":false,"flipY":false},{"tile":554,"color":2,"flipX":false,"flipY":false},{"tile":558,"color":2,"flipX":false,"flipY":false},{"tile":559,"color":2,"flipX":false,"flipY":false},{"tile":544,"color":2,"flipX":false,"flipY":false},{"tile":551,"color":2,"flipX":false,"flipY":false},{"tile":552,"color":2,"flipX":false,"flipY":false},{"tile":554,"color":2,"flipX":false,"flipY":false},{"tile":544,"color":2,"flipX":false,"flipY":false}]