[{"tile":1777,"color":6,"flipX":false,"flipY":false},{"tile":1776,"color":6,"flipX":false,"flipY":false},{"tile":1777,"color":6,"flipX":false,"flipY":false},{"tile":1709,"color":4,"flipX":false,"flipY":false},{"tile":1716,"color":4,"flipX":false,"flipY":false},{"tile":1717,"color":4,"flipX":false,"flipY":false},{"tile":1722,"color":4,"flipX":false,"flipY":false},{"tile":1703,"color":4,"flipX":false,"flipY":false},{"tile":1703,"color":4,"flipX":false,"flipY":false},{"tile":1723,"color":4,"flipX":false,"flipY":false},{"tile":1701,"color":4,"flipX":false,"flipY":false},{"tile":1702,"color":4,"flipX":false,"flipY":false},{"tile":1715,"color":4,"flipX":false,"flipY":false},{"tile":1778,"color":6,"flipX":false,"flipY":false},{"tile":1776,"color":6,"flipX":false,"flipY":false},{"tile":1777,"color":6,"flipX":false,"flipY":false},{"tile":1780,"color":6,"flipX":false,"flipY":false},{"tile":1779,"color":6,"flipX":false,"flipY":false},{"tile":1780,"color":6,"flipX":false,"flipY":false},{"tile":1709,"color":4,"flipX":false,"flipY":false},{"tile":1720,"color":4,"flipX":false,"flipY":false},{"tile":1721,"color":4,"flipX":false,"flipY":false},{"tile":1725,"color":4,"flipX":false,"flipY":false},{"tile":1726,"color":4,"flipX":false,"flipY":false},{"tile":1727,"color":4,"flipX":false,"flipY":false},{"tile":1728,"color":4,"flipX":false,"flipY":false},{"tile":1704,"color":4,"flipX":false,"flipY":false},{"tile":1705,"color":4,"flipX":false,"flipY":false},{"tile":1719,"color":4,"flipX":false,"flipY":false},{"tile":1781,"color":6,"flipX":false,"flipY":false},{"tile":1779,"color":6,"flipX":false,"flipY":false},{"tile":1780,"color":6,"flipX":false,"flipY":false},{"tile":1750,"color":6,"flipX":false,"flipY":false},{"tile":1751,"color":6,"flipX":false,"flipY":false},{"tile":1752,"color":6,"flipX":false,"flipY":false},{"tile":1709,"color":4,"flipX":false,"flipY":false},{"tile":1712,"color":4,"flipX":false,"flipY":false},{"tile":1724,"color":4,"flipX":false,"flipY":false},{"tile":1729,"color":4,"flipX":false,"flipY":false},{"tile":1730,"color":4,"flipX":false,"flipY":false},{"tile":1731,"color":4,"flipX":false,"flipY":false},{"tile":1732,"color":4,"flipX":false,"flipY":false},{"tile":1707,"color":4,"flipX":false,"flipY":false},{"tile":1708,"color":4,"flipX":false,"flipY":false},{"tile":1749,"color":4,"flipX":false,"flipY":false},{"tile":1750,"color":6,"flipX":false,"flipY":false},{"tile":1751,"color":6,"flipX":false,"flipY":false},{"tile":1752,"color":6,"flipX":false,"flipY":false},{"tile":1755,"color":6,"flipX":false,"flipY":false},{"tile":1756,"color":6,"flipX":false,"flipY":false},{"tile":1757,"color":6,"flipX":false,"flipY":false},{"tile":1709,"color":4,"flipX":false,"flipY":false},{"tile":1712,"color":4,"flipX":false,"flipY":false},{"tile":1706,"color":4,"flipX":false,"flipY":false},{"tile":1733,"color":4,"flipX":false,"flipY":false},{"tile":1738,"color":4,"flipX":false,"flipY":false},{"tile":1739,"color":4,"flipX":false,"flipY":false},{"tile":1734,"color":4,"flipX":false,"flipY":false},{"tile":1714,"color":4,"flipX":false,"flipY":false},{"tile":1748,"color":4,"flipX":false,"flipY":false},{"tile":1749,"color":4,"flipX":false,"flipY":false},{"tile":1755,"color":6,"flipX":false,"flipY":false},{"tile":1756,"color":6,"flipX":false,"flipY":false},{"tile":1757,"color":6,"flipX":false,"flipY":false},{"tile":1760,"color":6,"flipX":false,"flipY":false},{"tile":1761,"color":6,"flipX":false,"flipY":false},{"tile":1762,"color":6,"flipX":false,"flipY":false},{"tile":1709,"color":4,"flipX":false,"flipY":false},{"tile":1712,"color":4,"flipX":false,"flipY":false},{"tile":1706,"color":4,"flipX":false,"flipY":false},{"tile":1735,"color":4,"flipX":false,"flipY":false},{"tile":1738,"color":4,"flipX":false,"flipY":false},{"tile":1739,"color":4,"flipX":false,"flipY":false},{"tile":1736,"color":4,"flipX":false,"flipY":false},{"tile":1714,"color":4,"flipX":false,"flipY":false},{"tile":1748,"color":4,"flipX":false,"flipY":false},{"tile":1749,"color":4,"flipX":false,"flipY":false},{"tile":1760,"color":6,"flipX":false,"flipY":false},{"tile":1761,"color":6,"flipX":false,"flipY":false},{"tile":1762,"color":6,"flipX":false,"flipY":false},{"tile":1765,"color":6,"flipX":false,"flipY":false},{"tile":1766,"color":6,"flipX":false,"flipY":false},{"tile":1767,"color":6,"flipX":false,"flipY":false},{"tile":1709,"color":4,"flipX":false,"flipY":false},{"tile":1712,"color":4,"flipX":false,"flipY":false},{"tile":1706,"color":4,"flipX":false,"flipY":false},{"tile":1737,"color":4,"flipX":false,"flipY":false},{"tile":1738,"color":4,"flipX":false,"flipY":false},{"tile":1739,"color":4,"flipX":false,"flipY":false},{"tile":1740,"color":4,"flipX":false,"flipY":false},{"tile":1714,"color":4,"flipX":false,"flipY":false},{"tile":1748,"color":4,"flipX":false,"flipY":false},{"tile":1749,"color":4,"flipX":false,"flipY":false},{"tile":1765,"color":6,"flipX":false,"flipY":false},{"tile":1766,"color":6,"flipX":false,"flipY":false},{"tile":1767,"color":6,"flipX":false,"flipY":false},{"tile":1770,"color":6,"flipX":false,"flipY":false},{"tile":1771,"color":6,"flipX":false,"flipY":false},{"tile":1772,"color":6,"flipX":false,"flipY":false},{"tile":1709,"color":4,"flipX":false,"flipY":false},{"tile":1712,"color":4,"flipX":false,"flipY":false},{"tile":1710,"color":4,"flipX":false,"flipY":false},{"tile":1741,"color":4,"flipX":false,"flipY":false},{"tile":1742,"color":4,"flipX":false,"flipY":false},{"tile":1743,"color":4,"flipX":false,"flipY":false},{"tile":1744,"color":4,"flipX":false,"flipY":false},{"tile":1714,"color":4,"flipX":false,"flipY":false},{"tile":1748,"color":4,"flipX":false,"flipY":false},{"tile":1749,"color":4,"flipX":false,"flipY":false},{"tile":1770,"color":6,"flipX":false,"flipY":false},{"tile":1771,"color":6,"flipX":false,"flipY":false},{"tile":1772,"color":6,"flipX":false,"flipY":false},{"tile":1773,"color":6,"flipX":false,"flipY":false},{"tile":1774,"color":6,"flipX":false,"flipY":false},{"tile":1775,"color":6,"flipX":false,"flipY":false},{"tile":1711,"color":4,"flipX":false,"flipY":false},{"tile":1712,"color":4,"flipX":false,"flipY":false},{"tile":1713,"color":4,"flipX":false,"flipY":false},{"tile":1745,"color":4,"flipX":false,"flipY":false},{"tile":1745,"color":4,"flipX":false,"flipY":false},{"tile":1745,"color":4,"flipX":false,"flipY":false},{"tile":1746,"color":4,"flipX":false,"flipY":false},{"tile":1747,"color":4,"flipX":false,"flipY":false},{"tile":1748,"color":4,"flipX":false,"flipY":false},{"tile":1749,"color":4,"flipX":false,"flipY":false},{"tile":1773,"color":6,"flipX":false,"flipY":false},{"tile":1774,"color":6,"flipX":false,"flipY":false},{"tile":1775,"color":6,"flipX":false,"flipY":false},{"tile":1923,"color":0,"flipX":false,"flipY":false},{"tile":1924,"color":0,"flipX":false,"flipY":false},{"tile":1925,"color":0,"flipX":false,"flipY":false},{"tile":1926,"color":0,"flipX":false,"flipY":false},{"tile":1927,"color":0,"flipX":false,"flipY":false},{"tile":1928,"color":0,"flipX":false,"flipY":false},{"tile":1929,"color":0,"flipX":false,"flipY":false},{"tile":1929,"color":0,"flipX":false,"flipY":false},{"tile":1929,"color":0,"flipX":false,"flipY":false},{"tile":1930,"color":0,"flipX":false,"flipY":false},{"tile":1931,"color":0,"flipX":false,"flipY":false},{"tile":1932,"color":0,"flipX":false,"flipY":false},{"tile":1933,"color":0,"flipX":false,"flipY":false},{"tile":1923,"color":0,"flipX":false,"flipY":false},{"tile":1924,"color":0,"flipX":false,"flipY":false},{"tile":1925,"color":0,"flipX":false,"flipY":false},{"tile":1639,"color":2,"flipX":false,"flipY":false},{"tile":1639,"color":2,"flipX":false,"flipY":false},{"tile":1639,"color":2,"flipX":false,"flipY":false},{"tile":1639,"color":2,"flipX":false,"flipY":false},{"tile":1639,"color":2,"flipX":false,"flipY":false},{"tile":1639,"color":2,"flipX":false,"flipY":false},{"tile":1639,"color":2,"flipX":false,"flipY":false},{"tile":1639,"color":2,"flipX":false,"flipY":false},{"tile":1639,"color":2,"flipX":false,"flipY":false},{"tile":1639,"color":2,"flipX":false,"flipY":false},{"tile":1639,"color":2,"flipX":false,"flipY":false},{"tile":1639,"color":2,"flipX":false,"flipY":false},{"tile":1639,"color":2,"flipX":false,"flipY":false},{"tile":1934,"color":0,"flipX":false,"flipY":false},{"tile":1935,"color":0,"flipX":false,"flipY":false},{"tile":1936,"color":0,"flipX":false,"flipY":false},{"tile":1642,"color":2,"flipX":false,"flipY":false},{"tile":1642,"color":2,"flipX":false,"flipY":false},{"tile":1642,"color":2,"flipX":false,"flipY":false},{"tile":1642,"color":2,"flipX":false,"flipY":false},{"tile":1642,"color":2,"flipX":false,"flipY":false},{"tile":1642,"color":2,"flipX":false,"flipY":false},{"tile":1642,"color":2,"flipX":false,"flipY":false},{"tile":1642,"color":2,"flipX":false,"flipY":false},{"tile":1642,"color":2,"flipX":false,"flipY":false},{"tile":1642,"color":2,"flipX":false,"flipY":false},{"tile":1642,"color":2,"flipX":false,"flipY":false},{"tile":1642,"color":2,"flipX":false,"flipY":false},{"tile":1642,"color":2,"flipX":false,"flipY":false},{"tile":1643,"color":2,"flipX":false,"flipY":false},{"tile":1937,"color":0,"flipX":false,"flipY":false},{"tile":1938,"color":0,"flipX":false,"flipY":false},{"tile":1642,"color":2,"flipX":false,"flipY":false},{"tile":1642,"color":2,"flipX":false,"flipY":false},{"tile":1642,"color":2,"flipX":false,"flipY":false},{"tile":1642,"color":2,"flipX":false,"flipY":false},{"tile":1642,"color":2,"flipX":false,"flipY":false},{"tile":1642,"color":2,"flipX":false,"flipY":false},{"tile":1642,"color":2,"flipX":false,"flipY":false},{"tile":1642,"color":2,"flipX":false,"flipY":false},{"tile":1642,"color":2,"flipX":false,"flipY":false},{"tile":1642,"color":2,"flipX":false,"flipY":false},{"tile":1642,"color":2,"flipX":false,"flipY":false},{"tile":1642,"color":2,"flipX":false,"flipY":false},{"tile":1642,"color":2,"flipX":false,"flipY":false},{"tile":1452,"color":2,"flipX":false,"flipY":false},{"tile":1643,"color":2,"flipX":false,"flipY":false},{"tile":1939,"color":0,"flipX":false,"flipY":false},{"tile":1642,"color":2,"flipX":false,"flipY":false},{"tile":1642,"color":2,"flipX":false,"flipY":false},{"tile":1642,"color":2,"flipX":false,"flipY":false},{"tile":1642,"color":2,"flipX":false,"flipY":false},{"tile":1642,"color":2,"flipX":false,"flipY":false},{"tile":1642,"color":2,"flipX":false,"flipY":false},{"tile":1642,"color":2,"flipX":false,"flipY":false},{"tile":1642,"color":2,"flipX":false,"flipY":false},{"tile":1642,"color":2,"flipX":false,"flipY":false},{"tile":1642,"color":2,"flipX":false,"flipY":false},{"tile":1642,"color":2,"flipX":false,"flipY":false},{"tile":1642,"color":2,"flipX":false,"flipY":false},{"tile":1642,"color":2,"flipX":false,"flipY":false},{"tile":1452,"color":2,"flipX":false,"flipY":false},{"tile":1452,"color":2,"flipX":false,"flipY":false},{"tile":1643,"color":2,"flipX":false,"flipY":false},{"tile":1646,"color":2,"flipX":false,"flipY":false},{"tile":1646,"color":2,"flipX":false,"flipY":false},{"tile":1646,"color":2,"flipX":false,"flipY":false},{"tile":1646,"color":2,"flipX":false,"flipY":false},{"tile":1646,"color":2,"flipX":false,"flipY":false},{"tile":1646,"color":2,"flipX":false,"flipY":false},{"tile":1646,"color":2,"flipX":false,"flipY":false},{"tile":1646,"color":2,"flipX":false,"flipY":false},{"tile":1646,"color":2,"flipX":false,"flipY":false},{"tile":1646,"color":2,"flipX":false,"flipY":false},{"tile":1646,"color":2,"flipX":false,"flipY":false},{"tile":1646,"color":2,"flipX":false,"flipY":false},{"tile":1646,"color":2,"flipX":false,"flipY":false},{"tile":1647,"color":2,"flipX":false,"flipY":false},{"tile":1452,"color":2,"flipX":false,"flipY":false},{"tile":1452,"color":2,"flipX":false,"flipY":false},{"tile":1650,"color":2,"flipX":false,"flipY":false},{"tile":1650,"color":2,"flipX":false,"flipY":false},{"tile":1650,"color":2,"flipX":false,"flipY":false},{"tile":1650,"color":2,"flipX":false,"flipY":false},{"tile":1650,"color":2,"flipX":false,"flipY":false},{"tile":1650,"color":2,"flipX":false,"flipY":false},{"tile":1650,"color":2,"flipX":false,"flipY":false},{"tile":1650,"color":2,"flipX":false,"flipY":false},{"tile":1650,"color":2,"flipX":false,"flipY":false},{"tile":1650,"color":2,"flipX":false,"flipY":false},{"tile":1650,"color":2,"flipX":false,"flipY":false},{"tile":1650,"color":2,"flipX":false,"flipY":false},{"tile":1650,"color":2,"flipX":false,"flipY":false},{"tile":1651,"color":2,"flipX":false,"flipY":false},{"tile":1647,"color":2,"flipX":false,"flipY":false},{"tile":1452,"color":2,"flipX":false,"flipY":false},{"tile":1650,"color":2,"flipX":false,"flipY":false},{"tile":1650,"color":2,"flipX":false,"flipY":false},{"tile":1650,"color":2,"flipX":false,"flipY":false},{"tile":1650,"color":2,"flipX":false,"flipY":false},{"tile":1650,"color":2,"flipX":false,"flipY":false},{"tile":1650,"color":2,"flipX":false,"flipY":false},{"tile":1650,"color":2,"flipX":false,"flipY":false},{"tile":1650,"color":2,"flipX":false,"flipY":false},{"tile":1650,"color":2,"flipX":false,"flipY":false},{"tile":1650,"color":2,"flipX":false,"flipY":false},{"tile":1650,"color":2,"flipX":false,"flipY":false},{"tile":1650,"color":2,"flipX":false,"flipY":false},{"tile":1650,"color":2,"flipX":false,"flipY":false},{"tile":1650,"color":2,"flipX":false,"flipY":false},{"tile":1651,"color":2,"flipX":false,"flipY":false},{"tile":1647,"color":2,"flipX":false,"flipY":false},{"tile":1815,"color":0,"flipX":true,"flipY":false},{"tile":1792,"color":0,"flipX":true,"flipY":false},{"tile":1793,"color":0,"flipX":true,"flipY":false},{"tile":1793,"color":0,"flipX":true,"flipY":false},{"tile":1794,"color":0,"flipX":true,"flipY":false},{"tile":1815,"color":0,"flipX":true,"flipY":false},{"tile":1792,"color":0,"flipX":true,"flipY":false},{"tile":1793,"color":0,"flipX":true,"flipY":false},{"tile":1793,"color":0,"flipX":true,"flipY":false},{"tile":1794,"color":0,"flipX":true,"flipY":false},{"tile":1815,"color":0,"flipX":true,"flipY":false},{"tile":1792,"color":0,"flipX":true,"flipY":false},{"tile":1793,"color":0,"flipX":true,"flipY":false},{"tile":1793,"color":0,"flipX":true,"flipY":false},{"tile":1794,"color":0,"flipX":true,"flipY":false},{"tile":1815,"color":0,"flipX":true,"flipY":false},{"tile":1815,"color":0,"flipX":true,"flipY":false},{"tile":1795,"color":0,"flipX":true,"flipY":false},{"tile":1796,"color":0,"flipX":true,"flipY":false},{"tile":1797,"color":0,"flipX":true,"flipY":false},{"tile":1798,"color":0,"flipX":true,"flipY":false},{"tile":1815,"color":0,"flipX":true,"flipY":false},{"tile":1795,"color":0,"flipX":true,"flipY":false},{"tile":1796,"color":0,"flipX":true,"flipY":false},{"tile":1797,"color":0,"flipX":true,"flipY":false},{"tile":1798,"color":0,"flipX":true,"flipY":false},{"tile":1815,"color":0,"flipX":true,"flipY":false},{"tile":1795,"color":0,"flipX":true,"flipY":false},{"tile":1796,"color":0,"flipX":true,"flipY":false},{"tile":1797,"color":0,"flipX":true,"flipY":false},{"tile":1798,"color":0,"flipX":true,"flipY":false},{"tile":1815,"color":0,"flipX":true,"flipY":false},{"tile":1815,"color":0,"flipX":true,"flipY":false},{"tile":1799,"color":0,"flipX":true,"flipY":false},{"tile":1800,"color":0,"flipX":true,"flipY":false},{"tile":1801,"color":0,"flipX":true,"flipY":false},{"tile":1802,"color":0,"flipX":true,"flipY":false},{"tile":1815,"color":0,"flipX":true,"flipY":false},{"tile":1799,"color":0,"flipX":true,"flipY":false},{"tile":1800,"color":0,"flipX":true,"flipY":false},{"tile":1801,"color":0,"flipX":true,"flipY":false},{"tile":1802,"color":0,"flipX":true,"flipY":false},{"tile":1815,"color":0,"flipX":true,"flipY":false},{"tile":1799,"color":0,"flipX":true,"flipY":false},{"tile":1800,"color":0,"flipX":true,"flipY":false},{"tile":1801,"color":0,"flipX":true,"flipY":false},{"tile":1802,"color":0,"flipX":true,"flipY":false},{"tile":1815,"color":0,"flipX":true,"flipY":false},{"tile":1815,"color":0,"flipX":true,"flipY":false},{"tile":1803,"color":0,"flipX":true,"flipY":false},{"tile":1804,"color":0,"flipX":true,"flipY":false},{"tile":1805,"color":0,"flipX":true,"flipY":false},{"tile":1806,"color":0,"flipX":true,"flipY":false},{"tile":1815,"color":0,"flipX":true,"flipY":false},{"tile":1803,"color":0,"flipX":true,"flipY":false},{"tile":1804,"color":0,"flipX":true,"flipY":false},{"tile":1805,"color":0,"flipX":true,"flipY":false},{"tile":1806,"color":0,"flipX":true,"flipY":false},{"tile":1815,"color":0,"flipX":true,"flipY":false},{"tile":1803,"color":0,"flipX":true,"flipY":false},{"tile":1804,"color":0,"flipX":true,"flipY":false},{"tile":1805,"color":0,"flipX":true,"flipY":false},{"tile":1806,"color":0,"flipX":true,"flipY":false},{"tile":1815,"color":0,"flipX":true,"flipY":false},{"tile":1815,"color":0,"flipX":true,"flipY":false},{"tile":1807,"color":0,"flipX":true,"flipY":false},{"tile":1808,"color":0,"flipX":true,"flipY":false},{"tile":1809,"color":0,"flipX":true,"flipY":false},{"tile":1810,"color":0,"flipX":true,"flipY":false},{"tile":1815,"color":0,"flipX":true,"flipY":false},{"tile":1807,"color":0,"flipX":true,"flipY":false},{"tile":1808,"color":0,"flipX":true,"flipY":false},{"tile":1809,"color":0,"flipX":true,"flipY":false},{"tile":1810,"color":0,"flipX":true,"flipY":false},{"tile":1815,"color":0,"flipX":true,"flipY":false},{"tile":1807,"color":0,"flipX":true,"flipY":false},{"tile":1808,"color":0,"flipX":true,"flipY":false},{"tile":1809,"color":0,"flipX":true,"flipY":false},{"tile":1810,"color":0,"flipX":true,"flipY":false},{"tile":1815,"color":0,"flipX":true,"flipY":false},{"tile":1815,"color":0,"flipX":true,"flipY":false},{"tile":1811,"color":0,"flipX":true,"flipY":false},{"tile":1812,"color":0,"flipX":true,"flipY":false},{"tile":1813,"color":0,"flipX":true,"flipY":false},{"tile":1814,"color":0,"flipX":true,"flipY":false},{"tile":1815,"color":0,"flipX":true,"flipY":false},{"tile":1811,"color":0,"flipX":true,"flipY":false},{"tile":1812,"color":0,"flipX":true,"flipY":false},{"tile":1813,"color":0,"flipX":true,"flipY":false},{"tile":1814,"color":0,"flipX":true,"flipY":false},{"tile":1815,"color":0,"flipX":true,"flipY":false},{"tile":1811,"color":0,"flipX":true,"flipY":false},{"tile":1812,"color":0,"flipX":true,"flipY":false},{"tile":1813,"color":0,"flipX":true,"flipY":false},{"tile":1814,"color":0,"flipX":true,"flipY":false},{"tile":1815,"color":0,"flipX":true,"flipY":false},{"tile":1815,"color":0,"flipX":true,"flipY":false},{"tile":1816,"color":0,"flipX":true,"flipY":false},{"tile":1817,"color":0,"flipX":true,"flipY":false},{"tile":1818,"color":0,"flipX":true,"flipY":false},{"tile":1819,"color":0,"flipX":true,"flipY":false},{"tile":1815,"color":0,"flipX":true,"flipY":false},{"tile":1816,"color":0,"flipX":true,"flipY":false},{"tile":1817,"color":0,"flipX":true,"flipY":false},{"tile":1818,"color":0,"flipX":true,"flipY":false},{"tile":1819,"color":0,"flipX":true,"flipY":false},{"tile":1815,"color":0,"flipX":true,"flipY":false},{"tile":1816,"color":0,"flipX":true,"flipY":false},{"tile":1817,"color":0,"flipX":true,"flipY":false},{"tile":1818,"color":0,"flipX":true,"flipY":false},{"tile":1819,"color":0,"flipX":true,"flipY":false},{"tile":1815,"color":0,"flipX":true,"flipY":false},{"tile":1820,"color":0,"flipX":true,"flipY":false},{"tile":1886,"color":0,"flipX":false,"flipY":false},{"tile":1887,"color":0,"flipX":false,"flipY":false},{"tile":1888,"color":0,"flipX":false,"flipY":false},{"tile":1889,"color":0,"flipX":false,"flipY":false},{"tile":1820,"color":0,"flipX":true,"flipY":false},{"tile":1886,"color":0,"flipX":false,"flipY":false},{"tile":1887,"color":0,"flipX":false,"flipY":false},{"tile":1888,"color":0,"flipX":false,"flipY":false},{"tile":1889,"color":0,"flipX":false,"flipY":false},{"tile":1820,"color":0,"flipX":true,"flipY":false},{"tile":1886,"color":0,"flipX":false,"flipY":false},{"tile":1887,"color":0,"flipX":false,"flipY":false},{"tile":1888,"color":0,"flipX":false,"flipY":false},{"tile":1889,"color":0,"flipX":false,"flipY":false},{"tile":1820,"color":0,"flipX":true,"flipY":false},{"tile":1890,"color":0,"flipX":false,"flipY":false},{"tile":1891,"color":0,"flipX":false,"flipY":false},{"tile":1892,"color":0,"flipX":false,"flipY":false},{"tile":1893,"color":0,"flipX":false,"flipY":false},{"tile":1894,"color":0,"flipX":false,"flipY":false},{"tile":1890,"color":0,"flipX":false,"flipY":false},{"tile":1891,"color":0,"flipX":false,"flipY":false},{"tile":1892,"color":0,"flipX":false,"flipY":false},{"tile":1893,"color":0,"flipX":false,"flipY":false},{"tile":1894,"color":0,"flipX":false,"flipY":false},{"tile":1890,"color":0,"flipX":false,"flipY":false},{"tile":1891,"color":0,"flipX":false,"flipY":false},{"tile":1892,"color":0,"flipX":false,"flipY":false},{"tile":1893,"color":0,"flipX":false,"flipY":false},{"tile":1894,"color":0,"flipX":false,"flipY":false},{"tile":1890,"color":0,"flipX":false,"flipY":false},{"tile":1895,"color":0,"flipX":false,"flipY":false},{"tile":1897,"color":0,"flipX":false,"flipY":false},{"tile":1898,"color":0,"flipX":false,"flipY":false},{"tile":1899,"color":0,"flipX":false,"flipY":false},{"tile":1900,"color":0,"flipX":false,"flipY":false},{"tile":1895,"color":0,"flipX":false,"flipY":false},{"tile":1897,"color":0,"flipX":false,"flipY":false},{"tile":1898,"color":0,"flipX":false,"flipY":false},{"tile":1899,"color":0,"flipX":false,"flipY":false},{"tile":1900,"color":0,"flipX":false,"flipY":false},{"tile":1895,"color":0,"flipX":false,"flipY":false},{"tile":1897,"color":0,"flipX":false,"flipY":false},{"tile":1898,"color":0,"flipX":false,"flipY":false},{"tile":1899,"color":0,"flipX":false,"flipY":false},{"tile":1900,"color":0,"flipX":false,"flipY":false},{"tile":1895,"color":0,"flipX":false,"flipY":false},{"tile":1895,"color":0,"flipX":false,"flipY":false},{"tile":1902,"color":0,"flipX":false,"flipY":false},{"tile":1903,"color":0,"flipX":false,"flipY":false},{"tile":1904,"color":0,"flipX":false,"flipY":false},{"tile":1905,"color":0,"flipX":false,"flipY":false},{"tile":1895,"color":0,"flipX":false,"flipY":false},{"tile":1902,"color":0,"flipX":false,"flipY":false},{"tile":1903,"color":0,"flipX":false,"flipY":false},{"tile":1904,"color":0,"flipX":false,"flipY":false},{"tile":1905,"color":0,"flipX":false,"flipY":false},{"tile":1895,"color":0,"flipX":false,"flipY":false},{"tile":1902,"color":0,"flipX":false,"flipY":false},{"tile":1903,"color":0,"flipX":false,"flipY":false},{"tile":1904,"color":0,"flipX":false,"flipY":false},{"tile":1905,"color":0,"flipX":false,"flipY":false},{"tile":1895,"color":0,"flipX":false,"flipY":false},{"tile":1901,"color":0,"flipX":false,"flipY":false},{"tile":1908,"color":0,"flipX":false,"flipY":false},{"tile":1909,"color":0,"flipX":false,"flipY":false},{"tile":1910,"color":0,"flipX":false,"flipY":false},{"tile":1911,"color":0,"flipX":false,"flipY":false},{"tile":1901,"color":0,"flipX":false,"flipY":false},{"tile":1908,"color":0,"flipX":false,"flipY":false},{"tile":1909,"color":0,"flipX":false,"flipY":false},{"tile":1910,"color":0,"flipX":false,"flipY":false},{"tile":1911,"color":0,"flipX":false,"flipY":false},{"tile":1901,"color":0,"flipX":false,"flipY":false},{"tile":1908,"color":0,"flipX":false,"flipY":false},{"tile":1909,"color":0,"flipX":false,"flipY":false},{"tile":1910,"color":0,"flipX":false,"flipY":false},{"tile":1911,"color":0,"flipX":false,"flipY":false},{"tile":1901,"color":0,"flipX":false,"flipY":false},{"tile":1639,"color":2,"flipX":false,"flipY":false},{"tile":1639,"color":2,"flipX":false,"flipY":false},{"tile":1639,"color":2,"flipX":false,"flipY":false},{"tile":1639,"color":2,"flipX":false,"flipY":false},{"tile":1639,"color":2,"flipX":false,"flipY":false},{"tile":1639,"color":2,"flipX":false,"flipY":false},{"tile":1639,"color":2,"flipX":false,"flipY":false},{"tile":1639,"color":2,"flipX":false,"flipY":false},{"tile":1639,"color":2,"flipX":false,"flipY":false},{"tile":1639,"color":2,"flipX":false,"flipY":false},{"tile":1639,"color":2,"flipX":false,"flipY":false},{"tile":1639,"color":2,"flipX":false,"flipY":false},{"tile":1639,"color":2,"flipX":false,"flipY":false},{"tile":1639,"color":2,"flipX":false,"flipY":false},{"tile":1639,"color":2,"flipX":false,"flipY":false},{"tile":1639,"color":2,"flipX":false,"flipY":false},{"tile":1642,"color":2,"flipX":false,"flipY":false},{"tile":1642,"color":2,"flipX":false,"flipY":false},{"tile":1642,"color":2,"flipX":false,"flipY":false},{"tile":1642,"color":2,"flipX":false,"flipY":false},{"tile":1642,"color":2,"flipX":false,"flipY":false},{"tile":1642,"color":2,"flipX":false,"flipY":false},{"tile":1642,"color":2,"flipX":false,"flipY":false},{"tile":1642,"color":2,"flipX":false,"flipY":false},{"tile":1642,"color":2,"flipX":false,"flipY":false},{"tile":1642,"color":2,"flipX":false,"flipY":false},{"tile":1642,"color":2,"flipX":false,"flipY":false},{"tile":1642,"color":2,"flipX":false,"flipY":false},{"tile":1642,"color":2,"flipX":false,"flipY":false},{"tile":1642,"color":2,"flipX":false,"flipY":false},{"tile":1642,"color":2,"flipX":false,"flipY":false},{"tile":1642,"color":2,"flipX":false,"flipY":false},{"tile":1642,"color":2,"flipX":false,"flipY":false},{"tile":1642,"color":2,"flipX":false,"flipY":false},{"tile":1642,"color":2,"flipX":false,"flipY":false},{"tile":1642,"color":2,"flipX":false,"flipY":false},{"tile":1642,"color":2,"flipX":false,"flipY":false},{"tile":1642,"color":2,"flipX":false,"flipY":false},{"tile":1642,"color":2,"flipX":false,"flipY":false},{"tile":1642,"color":2,"flipX":false,"flipY":false},{"tile":1642,"color":2,"flipX":false,"flipY":false},{"tile":1642,"color":2,"flipX":false,"flipY":false},{"tile":1642,"color":2,"flipX":false,"flipY":false},{"tile":1642,"color":2,"flipX":false,"flipY":false},{"tile":1642,"color":2,"flipX":false,"flipY":false},{"tile":1642,"color":2,"flipX":false,"flipY":false},{"tile":1642,"color":2,"flipX":false,"flipY":false},{"tile":1642,"color":2,"flipX":false,"flipY":false},{"tile":1642,"color":2,"flipX":false,"flipY":false},{"tile":1642,"color":2,"flipX":false,"flipY":false},{"tile":1642,"color":2,"flipX":false,"flipY":false},{"tile":1642,"color":2,"flipX":false,"flipY":false},{"tile":1642,"color":2,"flipX":false,"flipY":false},{"tile":1642,"color":2,"flipX":false,"flipY":false},{"tile":1642,"color":2,"flipX":false,"flipY":false},{"tile":1642,"color":2,"flipX":false,"flipY":false},{"tile":1642,"color":2,"flipX":false,"flipY":false},{"tile":1642,"color":2,"flipX":false,"flipY":false},{"tile":1642,"color":2,"flipX":false,"flipY":false},{"tile":1642,"color":2,"flipX":false,"flipY":false},{"tile":1642,"color":2,"flipX":false,"flipY":false},{"tile":1642,"color":2,"flipX":false,"flipY":false},{"tile":1642,"color":2,"flipX":false,"flipY":false},{"tile":1642,"color":2,"flipX":false,"flipY":false},{"tile":1629,"color":2,"flipX":true,"flipY":false},{"tile":1630,"color":2,"flipX":true,"flipY":false},{"tile":1635,"color":2,"flipX":true,"flipY":false},{"tile":1684,"color":4,"flipX":true,"flipY":false},{"tile":1684,"color":4,"flipX":true,"flipY":false},{"tile":1684,"color":4,"flipX":true,"flipY":false},{"tile":1652,"color":4,"flipX":true,"flipY":false},{"tile":1684,"color":4,"flipX":true,"flipY":false},{"tile":1684,"color":4,"flipX":true,"flipY":false},{"tile":1684,"color":4,"flipX":true,"flipY":false},{"tile":1684,"color":4,"flipX":true,"flipY":false},{"tile":1696,"color":4,"flipX":true,"flipY":false},{"tile":1697,"color":4,"flipX":true,"flipY":false},{"tile":1600,"color":2,"flipX":true,"flipY":true},{"tile":1599,"color":2,"flipX":true,"flipY":true},{"tile":1578,"color":6,"flipX":true,"flipY":false},{"tile":1629,"color":2,"flipX":true,"flipY":false},{"tile":1630,"color":2,"flipX":true,"flipY":false},{"tile":1635,"color":2,"flipX":true,"flipY":false},{"tile":1678,"color":4,"flipX":true,"flipY":false},{"tile":1653,"color":4,"flipX":true,"flipY":false},{"tile":1654,"color":4,"flipX":true,"flipY":false},{"tile":1655,"color":4,"flipX":true,"flipY":false},{"tile":1656,"color":4,"flipX":true,"flipY":false},{"tile":1669,"color":4,"flipX":true,"flipY":false},{"tile":1657,"color":4,"flipX":true,"flipY":false},{"tile":1698,"color":4,"flipX":true,"flipY":false},{"tile":1694,"color":4,"flipX":true,"flipY":false},{"tile":1697,"color":4,"flipX":true,"flipY":false},{"tile":1600,"color":2,"flipX":true,"flipY":true},{"tile":1599,"color":2,"flipX":true,"flipY":true},{"tile":1580,"color":6,"flipX":true,"flipY":false},{"tile":1629,"color":2,"flipX":true,"flipY":false},{"tile":1630,"color":2,"flipX":true,"flipY":false},{"tile":1635,"color":2,"flipX":true,"flipY":false},{"tile":1678,"color":4,"flipX":true,"flipY":false},{"tile":1669,"color":4,"flipX":true,"flipY":false},{"tile":1658,"color":4,"flipX":true,"flipY":false},{"tile":1659,"color":4,"flipX":true,"flipY":false},{"tile":1669,"color":4,"flipX":true,"flipY":false},{"tile":1669,"color":4,"flipX":true,"flipY":false},{"tile":1669,"color":4,"flipX":true,"flipY":false},{"tile":1693,"color":4,"flipX":true,"flipY":false},{"tile":1694,"color":4,"flipX":true,"flipY":false},{"tile":1697,"color":4,"flipX":true,"flipY":false},{"tile":1600,"color":2,"flipX":true,"flipY":true},{"tile":1599,"color":2,"flipX":true,"flipY":true},{"tile":1586,"color":6,"flipX":true,"flipY":false},{"tile":1629,"color":2,"flipX":true,"flipY":false},{"tile":1630,"color":2,"flipX":true,"flipY":false},{"tile":1635,"color":2,"flipX":true,"flipY":false},{"tile":1678,"color":4,"flipX":true,"flipY":false},{"tile":1669,"color":4,"flipX":true,"flipY":false},{"tile":1660,"color":4,"flipX":true,"flipY":false},{"tile":1661,"color":4,"flipX":true,"flipY":false},{"tile":1662,"color":4,"flipX":true,"flipY":false},{"tile":1669,"color":4,"flipX":true,"flipY":false},{"tile":1669,"color":4,"flipX":true,"flipY":false},{"tile":1693,"color":4,"flipX":true,"flipY":false},{"tile":1694,"color":4,"flipX":true,"flipY":false},{"tile":1697,"color":4,"flipX":true,"flipY":false},{"tile":1600,"color":2,"flipX":true,"flipY":true},{"tile":1599,"color":2,"flipX":true,"flipY":true},{"tile":1594,"color":6,"flipX":true,"flipY":false},{"tile":1629,"color":2,"flipX":true,"flipY":false},{"tile":1630,"color":2,"flipX":true,"flipY":false},{"tile":1635,"color":2,"flipX":true,"flipY":false},{"tile":1678,"color":4,"flipX":true,"flipY":false},{"tile":1669,"color":4,"flipX":true,"flipY":false},{"tile":1663,"color":4,"flipX":true,"flipY":false},{"tile":1664,"color":4,"flipX":true,"flipY":false},{"tile":1665,"color":4,"flipX":true,"flipY":false},{"tile":1669,"color":4,"flipX":true,"flipY":false},{"tile":1669,"color":4,"flipX":true,"flipY":false},{"tile":1693,"color":4,"flipX":true,"flipY":false},{"tile":1694,"color":4,"flipX":true,"flipY":false},{"tile":1697,"color":4,"flipX":true,"flipY":false},{"tile":1604,"color":2,"flipX":true,"flipY":true},{"tile":1603,"color":2,"flipX":true,"flipY":true},{"tile":1602,"color":2,"flipX":true,"flipY":true},{"tile":1629,"color":2,"flipX":true,"flipY":false},{"tile":1630,"color":2,"flipX":true,"flipY":false},{"tile":1635,"color":2,"flipX":true,"flipY":false},{"tile":1678,"color":4,"flipX":true,"flipY":false},{"tile":1669,"color":4,"flipX":true,"flipY":false},{"tile":1666,"color":4,"flipX":true,"flipY":false},{"tile":1667,"color":4,"flipX":true,"flipY":false},{"tile":1668,"color":4,"flipX":true,"flipY":false},{"tile":1669,"color":4,"flipX":true,"flipY":false},{"tile":1669,"color":4,"flipX":true,"flipY":false},{"tile":1693,"color":4,"flipX":true,"flipY":false},{"tile":1694,"color":4,"flipX":true,"flipY":false},{"tile":1697,"color":4,"flipX":true,"flipY":false},{"tile":1606,"color":2,"flipX":true,"flipY":false},{"tile":1606,"color":2,"flipX":true,"flipY":false},{"tile":1606,"color":2,"flipX":true,"flipY":false},{"tile":1629,"color":2,"flipX":true,"flipY":false},{"tile":1630,"color":2,"flipX":true,"flipY":false},{"tile":1635,"color":2,"flipX":true,"flipY":false},{"tile":1678,"color":4,"flipX":true,"flipY":false},{"tile":1669,"color":4,"flipX":true,"flipY":false},{"tile":1670,"color":4,"flipX":true,"flipY":false},{"tile":1671,"color":4,"flipX":true,"flipY":false},{"tile":1672,"color":4,"flipX":true,"flipY":false},{"tile":1673,"color":4,"flipX":true,"flipY":false},{"tile":1669,"color":4,"flipX":true,"flipY":false},{"tile":1693,"color":4,"flipX":true,"flipY":false},{"tile":1694,"color":4,"flipX":true,"flipY":false},{"tile":1697,"color":4,"flipX":true,"flipY":false},{"tile":1609,"color":6,"flipX":false,"flipY":false},{"tile":1611,"color":6,"flipX":false,"flipY":false},{"tile":1612,"color":6,"flipX":false,"flipY":false},{"tile":1631,"color":2,"flipX":true,"flipY":false},{"tile":1632,"color":2,"flipX":true,"flipY":false},{"tile":1635,"color":2,"flipX":true,"flipY":false},{"tile":1678,"color":4,"flipX":true,"flipY":false},{"tile":1669,"color":4,"flipX":true,"flipY":false},{"tile":1674,"color":4,"flipX":true,"flipY":false},{"tile":1675,"color":4,"flipX":true,"flipY":false},{"tile":1676,"color":4,"flipX":true,"flipY":false},{"tile":1677,"color":4,"flipX":true,"flipY":false},{"tile":1669,"color":4,"flipX":true,"flipY":false},{"tile":1693,"color":4,"flipX":true,"flipY":false},{"tile":1694,"color":4,"flipX":true,"flipY":false},{"tile":1697,"color":4,"flipX":true,"flipY":false},{"tile":1613,"color":6,"flipX":false,"flipY":false},{"tile":1615,"color":6,"flipX":false,"flipY":false},{"tile":1616,"color":6,"flipX":false,"flipY":false},{"tile":1633,"color":2,"flipX":true,"flipY":false},{"tile":1634,"color":2,"flipX":true,"flipY":false},{"tile":1635,"color":2,"flipX":true,"flipY":false},{"tile":1678,"color":4,"flipX":true,"flipY":false},{"tile":1679,"color":4,"flipX":true,"flipY":false},{"tile":1680,"color":4,"flipX":true,"flipY":false},{"tile":1681,"color":4,"flipX":true,"flipY":false},{"tile":1682,"color":4,"flipX":true,"flipY":false},{"tile":1683,"color":4,"flipX":true,"flipY":false},{"tile":1451,"color":4,"flipX":true,"flipY":false},{"tile":1695,"color":4,"flipX":true,"flipY":false},{"tile":1694,"color":4,"flipX":true,"flipY":false},{"tile":1697,"color":4,"flipX":true,"flipY":false},{"tile":1617,"color":6,"flipX":false,"flipY":false},{"tile":1619,"color":6,"flipX":false,"flipY":false},{"tile":1620,"color":6,"flipX":false,"flipY":false},{"tile":1896,"color":0,"flipX":false,"flipY":false},{"tile":1636,"color":2,"flipX":true,"flipY":false},{"tile":1637,"color":2,"flipX":true,"flipY":false},{"tile":1684,"color":4,"flipX":true,"flipY":false},{"tile":1684,"color":4,"flipX":true,"flipY":false},{"tile":1685,"color":4,"flipX":true,"flipY":false},{"tile":1686,"color":4,"flipX":true,"flipY":false},{"tile":1687,"color":4,"flipX":true,"flipY":false},{"tile":1688,"color":4,"flipX":true,"flipY":false},{"tile":1684,"color":4,"flipX":true,"flipY":false},{"tile":1684,"color":4,"flipX":true,"flipY":false},{"tile":1696,"color":4,"flipX":true,"flipY":false},{"tile":1697,"color":4,"flipX":true,"flipY":false},{"tile":1621,"color":6,"flipX":false,"flipY":false},{"tile":1623,"color":6,"flipX":false,"flipY":false},{"tile":1624,"color":6,"flipX":false,"flipY":false},{"tile":1896,"color":0,"flipX":false,"flipY":false},{"tile":1896,"color":0,"flipX":false,"flipY":false},{"tile":1638,"color":2,"flipX":true,"flipY":false},{"tile":1918,"color":0,"flipX":false,"flipY":false},{"tile":1918,"color":0,"flipX":false,"flipY":false},{"tile":1689,"color":4,"flipX":true,"flipY":false},{"tile":1690,"color":4,"flipX":true,"flipY":false},{"tile":1691,"color":4,"flipX":true,"flipY":false},{"tile":1692,"color":4,"flipX":true,"flipY":false},{"tile":1918,"color":0,"flipX":false,"flipY":false},{"tile":1918,"color":0,"flipX":false,"flipY":false},{"tile":1699,"color":4,"flipX":true,"flipY":false},{"tile":1700,"color":4,"flipX":true,"flipY":false},{"tile":1625,"color":6,"flipX":false,"flipY":false},{"tile":1627,"color":6,"flipX":false,"flipY":false},{"tile":1628,"color":6,"flipX":false,"flipY":false},{"tile":1920,"color":0,"flipX":false,"flipY":false},{"tile":1920,"color":0,"flipX":false,"flipY":false},{"tile":1890,"color":0,"flipX":false,"flipY":false},{"tile":1920,"color":0,"flipX":false,"flipY":false},{"tile":1920,"color":0,"flipX":false,"flipY":false},{"tile":1914,"color":0,"flipX":false,"flipY":false},{"tile":1915,"color":0,"flipX":false,"flipY":false},{"tile":1916,"color":0,"flipX":false,"flipY":false},{"tile":1917,"color":0,"flipX":false,"flipY":false},{"tile":1920,"color":0,"flipX":false,"flipY":false},{"tile":1920,"color":0,"flipX":false,"flipY":false},{"tile":1921,"color":0,"flipX":false,"flipY":false},{"tile":1922,"color":0,"flipX":false,"flipY":false},{"tile":1907,"color":0,"flipX":false,"flipY":false},{"tile":1912,"color":0,"flipX":false,"flipY":false},{"tile":1913,"color":0,"flipX":false,"flipY":false},{"tile":1639,"color":2,"flipX":false,"flipY":false},{"tile":1639,"color":2,"flipX":false,"flipY":false},{"tile":1639,"color":2,"flipX":false,"flipY":false},{"tile":1639,"color":2,"flipX":false,"flipY":false},{"tile":1639,"color":2,"flipX":false,"flipY":false},{"tile":1639,"color":2,"flipX":false,"flipY":false},{"tile":1639,"color":2,"flipX":false,"flipY":false},{"tile":1639,"color":2,"flipX":false,"flipY":false},{"tile":1639,"color":2,"flipX":false,"flipY":false},{"tile":1639,"color":2,"flipX":false,"flipY":false},{"tile":1639,"color":2,"flipX":false,"flipY":false},{"tile":1639,"color":2,"flipX":false,"flipY":false},{"tile":1639,"color":2,"flipX":false,"flipY":false},{"tile":1639,"color":2,"flipX":false,"flipY":false},{"tile":1639,"color":2,"flipX":false,"flipY":false},{"tile":1639,"color":2,"flipX":false,"flipY":false},{"tile":1642,"color":2,"flipX":false,"flipY":false},{"tile":1642,"color":2,"flipX":false,"flipY":false},{"tile":1642,"color":2,"flipX":false,"flipY":false},{"tile":1642,"color":2,"flipX":false,"flipY":false},{"tile":1642,"color":2,"flipX":false,"flipY":false},{"tile":1642,"color":2,"flipX":false,"flipY":false},{"tile":1642,"color":2,"flipX":false,"flipY":false},{"tile":1642,"color":2,"flipX":false,"flipY":false},{"tile":1642,"color":2,"flipX":false,"flipY":false},{"tile":1642,"color":2,"flipX":false,"flipY":false},{"tile":1642,"color":2,"flipX":false,"flipY":false},{"tile":1642,"color":2,"flipX":false,"flipY":false},{"tile":1642,"color":2,"flipX":false,"flipY":false},{"tile":1642,"color":2,"flipX":false,"flipY":false},{"tile":1642,"color":2,"flipX":false,"flipY":false},{"tile":1642,"color":2,"flipX":false,"flipY":false},{"tile":1642,"color":2,"flipX":false,"flipY":false},{"tile":1642,"color":2,"flipX":false,"flipY":false},{"tile":1642,"color":2,"flipX":false,"flipY":false},{"tile":1642,"color":2,"flipX":false,"flipY":false},{"tile":1642,"color":2,"flipX":false,"flipY":false},{"tile":1642,"color":2,"flipX":false,"flipY":false},{"tile":1642,"color":2,"flipX":false,"flipY":false},{"tile":1642,"color":2,"flipX":false,"flipY":false},{"tile":1642,"color":2,"flipX":false,"flipY":false},{"tile":1642,"color":2,"flipX":false,"flipY":false},{"tile":1642,"color":2,"flipX":false,"flipY":false},{"tile":1642,"color":2,"flipX":false,"flipY":false},{"tile":1642,"color":2,"flipX":false,"flipY":false},{"tile":1642,"color":2,"flipX":false,"flipY":false},{"tile":1642,"color":2,"flipX":false,"flipY":false},{"tile":1642,"color":2,"flipX":false,"flipY":false},{"tile":1642,"color":2,"flipX":false,"flipY":false},{"tile":1642,"color":2,"flipX":false,"flipY":false},{"tile":1642,"color":2,"flipX":false,"flipY":false},{"tile":1642,"color":2,"flipX":false,"flipY":false},{"tile":1642,"color":2,"flipX":false,"flipY":false},{"tile":1642,"color":2,"flipX":false,"flipY":false},{"tile":1642,"color":2,"flipX":false,"flipY":false},{"tile":1642,"color":2,"flipX":false,"flipY":false},{"tile":1642,"color":2,"flipX":false,"flipY":false},{"tile":1642,"color":2,"flipX":false,"flipY":false},{"tile":1642,"color":2,"flipX":false,"flipY":false},{"tile":1642,"color":2,"flipX":false,"flipY":false},{"tile":1642,"color":2,"flipX":false,"flipY":false},{"tile":1642,"color":2,"flipX":false,"flipY":false},{"tile":1642,"color":2,"flipX":false,"flipY":false},{"tile":1642,"color":2,"flipX":false,"flipY":false},{"tile":1578,"color":6,"flipX":true,"flipY":false},{"tile":1578,"color":6,"flipX":true,"flipY":false},{"tile":1576,"color":6,"flipX":true,"flipY":false},{"tile":1577,"color":6,"flipX":true,"flipY":false},{"tile":1578,"color":6,"flipX":true,"flipY":false},{"tile":1578,"color":6,"flipX":true,"flipY":false},{"tile":1579,"color":6,"flipX":true,"flipY":false},{"tile":1592,"color":6,"flipX":true,"flipY":false},{"tile":1599,"color":2,"flipX":true,"flipY":false},{"tile":1600,"color":2,"flipX":true,"flipY":false},{"tile":1607,"color":2,"flipX":true,"flipY":false},{"tile":1596,"color":2,"flipX":true,"flipY":false},{"tile":1607,"color":2,"flipX":true,"flipY":false},{"tile":1569,"color":2,"flipX":true,"flipY":false},{"tile":1569,"color":2,"flipX":true,"flipY":false},{"tile":1569,"color":2,"flipX":true,"flipY":false},{"tile":1580,"color":6,"flipX":true,"flipY":false},{"tile":1580,"color":6,"flipX":true,"flipY":false},{"tile":1581,"color":6,"flipX":true,"flipY":false},{"tile":1582,"color":6,"flipX":true,"flipY":false},{"tile":1583,"color":6,"flipX":true,"flipY":false},{"tile":1584,"color":6,"flipX":true,"flipY":false},{"tile":1585,"color":6,"flipX":true,"flipY":false},{"tile":1593,"color":6,"flipX":true,"flipY":false},{"tile":1599,"color":2,"flipX":true,"flipY":false},{"tile":1600,"color":2,"flipX":true,"flipY":false},{"tile":1607,"color":2,"flipX":true,"flipY":false},{"tile":1597,"color":2,"flipX":true,"flipY":false},{"tile":1607,"color":2,"flipX":true,"flipY":false},{"tile":1569,"color":2,"flipX":true,"flipY":false},{"tile":1569,"color":2,"flipX":true,"flipY":false},{"tile":1569,"color":2,"flipX":true,"flipY":false},{"tile":1587,"color":6,"flipX":true,"flipY":false},{"tile":1586,"color":6,"flipX":true,"flipY":false},{"tile":1587,"color":6,"flipX":true,"flipY":false},{"tile":1588,"color":6,"flipX":true,"flipY":false},{"tile":1589,"color":6,"flipX":true,"flipY":false},{"tile":1590,"color":6,"flipX":true,"flipY":false},{"tile":1591,"color":6,"flipX":true,"flipY":false},{"tile":1594,"color":6,"flipX":true,"flipY":false},{"tile":1599,"color":2,"flipX":true,"flipY":false},{"tile":1600,"color":2,"flipX":true,"flipY":false},{"tile":1607,"color":2,"flipX":true,"flipY":false},{"tile":1596,"color":2,"flipX":true,"flipY":false},{"tile":1607,"color":2,"flipX":true,"flipY":false},{"tile":1569,"color":2,"flipX":true,"flipY":false},{"tile":1569,"color":2,"flipX":true,"flipY":false},{"tile":1569,"color":2,"flipX":true,"flipY":false},{"tile":1594,"color":6,"flipX":true,"flipY":false},{"tile":1594,"color":6,"flipX":true,"flipY":false},{"tile":1594,"color":6,"flipX":true,"flipY":false},{"tile":1594,"color":6,"flipX":true,"flipY":false},{"tile":1594,"color":6,"flipX":true,"flipY":false},{"tile":1594,"color":6,"flipX":true,"flipY":false},{"tile":1594,"color":6,"flipX":true,"flipY":false},{"tile":1594,"color":6,"flipX":true,"flipY":false},{"tile":1599,"color":2,"flipX":true,"flipY":false},{"tile":1600,"color":2,"flipX":true,"flipY":false},{"tile":1607,"color":2,"flipX":true,"flipY":false},{"tile":1597,"color":2,"flipX":true,"flipY":false},{"tile":1607,"color":2,"flipX":true,"flipY":false},{"tile":1569,"color":2,"flipX":true,"flipY":false},{"tile":1569,"color":2,"flipX":true,"flipY":false},{"tile":1569,"color":2,"flipX":true,"flipY":false},{"tile":1601,"color":2,"flipX":true,"flipY":false},{"tile":1601,"color":2,"flipX":true,"flipY":false},{"tile":1601,"color":2,"flipX":true,"flipY":false},{"tile":1601,"color":2,"flipX":true,"flipY":false},{"tile":1601,"color":2,"flipX":true,"flipY":false},{"tile":1601,"color":2,"flipX":true,"flipY":false},{"tile":1601,"color":2,"flipX":true,"flipY":false},{"tile":1602,"color":2,"flipX":true,"flipY":false},{"tile":1603,"color":2,"flipX":true,"flipY":false},{"tile":1604,"color":2,"flipX":true,"flipY":false},{"tile":1607,"color":2,"flipX":true,"flipY":false},{"tile":1596,"color":2,"flipX":true,"flipY":false},{"tile":1607,"color":2,"flipX":true,"flipY":false},{"tile":1564,"color":2,"flipX":true,"flipY":false},{"tile":1565,"color":2,"flipX":true,"flipY":false},{"tile":1561,"color":2,"flipX":true,"flipY":false},{"tile":1606,"color":2,"flipX":true,"flipY":false},{"tile":1606,"color":2,"flipX":true,"flipY":false},{"tile":1606,"color":2,"flipX":true,"flipY":false},{"tile":1606,"color":2,"flipX":true,"flipY":false},{"tile":1606,"color":2,"flipX":true,"flipY":false},{"tile":1606,"color":2,"flipX":true,"flipY":false},{"tile":1606,"color":2,"flipX":true,"flipY":false},{"tile":1606,"color":2,"flipX":true,"flipY":false},{"tile":1606,"color":2,"flipX":true,"flipY":false},{"tile":1606,"color":2,"flipX":true,"flipY":false},{"tile":1607,"color":2,"flipX":true,"flipY":false},{"tile":1597,"color":2,"flipX":true,"flipY":false},{"tile":1607,"color":2,"flipX":true,"flipY":false},{"tile":1568,"color":2,"flipX":true,"flipY":false},{"tile":1566,"color":2,"flipX":true,"flipY":false},{"tile":1566,"color":2,"flipX":true,"flipY":false},{"tile":1610,"color":6,"flipX":false,"flipY":false},{"tile":1611,"color":6,"flipX":false,"flipY":false},{"tile":1612,"color":6,"flipX":false,"flipY":false},{"tile":1605,"color":2,"flipX":true,"flipY":false},{"tile":1609,"color":6,"flipX":false,"flipY":false},{"tile":1611,"color":6,"flipX":false,"flipY":false},{"tile":1612,"color":6,"flipX":false,"flipY":false},{"tile":1610,"color":6,"flipX":false,"flipY":false},{"tile":1611,"color":6,"flipX":false,"flipY":false},{"tile":1612,"color":6,"flipX":false,"flipY":false},{"tile":1607,"color":2,"flipX":true,"flipY":false},{"tile":1596,"color":2,"flipX":true,"flipY":false},{"tile":1607,"color":2,"flipX":true,"flipY":false},{"tile":1571,"color":2,"flipX":true,"flipY":false},{"tile":1569,"color":2,"flipX":true,"flipY":false},{"tile":1569,"color":2,"flipX":true,"flipY":false},{"tile":1614,"color":6,"flipX":false,"flipY":false},{"tile":1615,"color":6,"flipX":false,"flipY":false},{"tile":1616,"color":6,"flipX":false,"flipY":false},{"tile":1607,"color":2,"flipX":true,"flipY":false},{"tile":1613,"color":6,"flipX":false,"flipY":false},{"tile":1615,"color":6,"flipX":false,"flipY":false},{"tile":1616,"color":6,"flipX":false,"flipY":false},{"tile":1614,"color":6,"flipX":false,"flipY":false},{"tile":1615,"color":6,"flipX":false,"flipY":false},{"tile":1616,"color":6,"flipX":false,"flipY":false},{"tile":1607,"color":2,"flipX":true,"flipY":false},{"tile":1597,"color":2,"flipX":true,"flipY":false},{"tile":1607,"color":2,"flipX":true,"flipY":false},{"tile":1571,"color":2,"flipX":true,"flipY":false},{"tile":1569,"color":2,"flipX":true,"flipY":false},{"tile":1569,"color":2,"flipX":true,"flipY":false},{"tile":1618,"color":6,"flipX":false,"flipY":false},{"tile":1619,"color":6,"flipX":false,"flipY":false},{"tile":1620,"color":6,"flipX":false,"flipY":false},{"tile":1607,"color":2,"flipX":true,"flipY":false},{"tile":1617,"color":6,"flipX":false,"flipY":false},{"tile":1619,"color":6,"flipX":false,"flipY":false},{"tile":1620,"color":6,"flipX":false,"flipY":false},{"tile":1618,"color":6,"flipX":false,"flipY":false},{"tile":1619,"color":6,"flipX":false,"flipY":false},{"tile":1620,"color":6,"flipX":false,"flipY":false},{"tile":1607,"color":2,"flipX":true,"flipY":false},{"tile":1596,"color":2,"flipX":true,"flipY":false},{"tile":1607,"color":2,"flipX":true,"flipY":false},{"tile":1571,"color":2,"flipX":true,"flipY":false},{"tile":1569,"color":2,"flipX":true,"flipY":false},{"tile":1569,"color":2,"flipX":true,"flipY":false},{"tile":1622,"color":6,"flipX":false,"flipY":false},{"tile":1623,"color":6,"flipX":false,"flipY":false},{"tile":1624,"color":6,"flipX":false,"flipY":false},{"tile":1607,"color":2,"flipX":true,"flipY":false},{"tile":1621,"color":6,"flipX":false,"flipY":false},{"tile":1623,"color":6,"flipX":false,"flipY":false},{"tile":1624,"color":6,"flipX":false,"flipY":false},{"tile":1622,"color":6,"flipX":false,"flipY":false},{"tile":1623,"color":6,"flipX":false,"flipY":false},{"tile":1624,"color":6,"flipX":false,"flipY":false},{"tile":1607,"color":2,"flipX":true,"flipY":false},{"tile":1597,"color":2,"flipX":true,"flipY":false},{"tile":1607,"color":2,"flipX":true,"flipY":false},{"tile":1571,"color":2,"flipX":true,"flipY":false},{"tile":1569,"color":2,"flipX":true,"flipY":false},{"tile":1569,"color":2,"flipX":true,"flipY":false},{"tile":1626,"color":6,"flipX":false,"flipY":false},{"tile":1627,"color":6,"flipX":false,"flipY":false},{"tile":1628,"color":6,"flipX":false,"flipY":false},{"tile":1608,"color":2,"flipX":true,"flipY":false},{"tile":1625,"color":6,"flipX":false,"flipY":false},{"tile":1627,"color":6,"flipX":false,"flipY":false},{"tile":1628,"color":6,"flipX":false,"flipY":false},{"tile":1626,"color":6,"flipX":false,"flipY":false},{"tile":1627,"color":6,"flipX":false,"flipY":false},{"tile":1628,"color":6,"flipX":false,"flipY":false},{"tile":1608,"color":2,"flipX":true,"flipY":false},{"tile":1598,"color":2,"flipX":true,"flipY":false},{"tile":1607,"color":2,"flipX":true,"flipY":false},{"tile":1571,"color":2,"flipX":true,"flipY":false},{"tile":1569,"color":2,"flipX":true,"flipY":false},{"tile":1569,"color":2,"flipX":true,"flipY":false},{"tile":1919,"color":0,"flipX":false,"flipY":false},{"tile":1912,"color":0,"flipX":false,"flipY":false},{"tile":1913,"color":0,"flipX":false,"flipY":false},{"tile":1906,"color":0,"flipX":false,"flipY":false},{"tile":1907,"color":0,"flipX":false,"flipY":false},{"tile":1912,"color":0,"flipX":false,"flipY":false},{"tile":1913,"color":0,"flipX":false,"flipY":false},{"tile":1919,"color":0,"flipX":false,"flipY":false},{"tile":1912,"color":0,"flipX":false,"flipY":false},{"tile":1913,"color":0,"flipX":false,"flipY":false},{"tile":1906,"color":0,"flipX":false,"flipY":false},{"tile":1896,"color":0,"flipX":false,"flipY":false},{"tile":1608,"color":2,"flipX":true,"flipY":false},{"tile":1573,"color":2,"flipX":true,"flipY":false},{"tile":1574,"color":2,"flipX":true,"flipY":false},{"tile":1574,"color":2,"flipX":true,"flipY":false},{"tile":1639,"color":2,"flipX":false,"flipY":false},{"tile":1640,"color":2,"flipX":false,"flipY":false},{"tile":1641,"color":2,"flipX":false,"flipY":false},{"tile":1640,"color":2,"flipX":false,"flipY":true},{"tile":1639,"color":2,"flipX":false,"flipY":false},{"tile":1639,"color":2,"flipX":false,"flipY":false},{"tile":1639,"color":2,"flipX":false,"flipY":false},{"tile":1639,"color":2,"flipX":false,"flipY":false},{"tile":1639,"color":2,"flipX":false,"flipY":false},{"tile":1639,"color":2,"flipX":false,"flipY":false},{"tile":1639,"color":2,"flipX":false,"flipY":false},{"tile":1639,"color":2,"flipX":false,"flipY":false},{"tile":1639,"color":2,"flipX":false,"flipY":false},{"tile":1639,"color":2,"flipX":false,"flipY":false},{"tile":1639,"color":2,"flipX":false,"flipY":false},{"tile":1639,"color":2,"flipX":false,"flipY":false},{"tile":1642,"color":2,"flipX":false,"flipY":false},{"tile":1644,"color":2,"flipX":false,"flipY":false},{"tile":1645,"color":2,"flipX":false,"flipY":false},{"tile":1644,"color":2,"flipX":false,"flipY":true},{"tile":1642,"color":2,"flipX":false,"flipY":false},{"tile":1642,"color":2,"flipX":false,"flipY":false},{"tile":1642,"color":2,"flipX":false,"flipY":false},{"tile":1642,"color":2,"flipX":false,"flipY":false},{"tile":1642,"color":2,"flipX":false,"flipY":false},{"tile":1642,"color":2,"flipX":false,"flipY":false},{"tile":1642,"color":2,"flipX":false,"flipY":false},{"tile":1642,"color":2,"flipX":false,"flipY":false},{"tile":1642,"color":2,"flipX":false,"flipY":false},{"tile":1642,"color":2,"flipX":false,"flipY":false},{"tile":1642,"color":2,"flipX":false,"flipY":false},{"tile":1642,"color":2,"flipX":false,"flipY":false},{"tile":1642,"color":2,"flipX":false,"flipY":false},{"tile":1648,"color":2,"flipX":false,"flipY":false},{"tile":1649,"color":2,"flipX":false,"flipY":false},{"tile":1648,"color":2,"flipX":false,"flipY":true},{"tile":1642,"color":2,"flipX":false,"flipY":false},{"tile":1642,"color":2,"flipX":false,"flipY":false},{"tile":1642,"color":2,"flipX":false,"flipY":false},{"tile":1642,"color":2,"flipX":false,"flipY":false},{"tile":1642,"color":2,"flipX":false,"flipY":false},{"tile":1642,"color":2,"flipX":false,"flipY":false},{"tile":1642,"color":2,"flipX":false,"flipY":false},{"tile":1642,"color":2,"flipX":false,"flipY":false},{"tile":1642,"color":2,"flipX":false,"flipY":false},{"tile":1642,"color":2,"flipX":false,"flipY":false},{"tile":1642,"color":2,"flipX":false,"flipY":false},{"tile":1642,"color":2,"flipX":false,"flipY":false},{"tile":1642,"color":2,"flipX":false,"flipY":false},{"tile":1644,"color":2,"flipX":false,"flipY":false},{"tile":1645,"color":2,"flipX":false,"flipY":false},{"tile":1644,"color":2,"flipX":false,"flipY":true},{"tile":1642,"color":2,"flipX":false,"flipY":false},{"tile":1642,"color":2,"flipX":false,"flipY":false},{"tile":1642,"color":2,"flipX":false,"flipY":false},{"tile":1642,"color":2,"flipX":false,"flipY":false},{"tile":1642,"color":2,"flipX":false,"flipY":false},{"tile":1642,"color":2,"flipX":false,"flipY":false},{"tile":1642,"color":2,"flipX":false,"flipY":false},{"tile":1642,"color":2,"flipX":false,"flipY":false},{"tile":1642,"color":2,"flipX":false,"flipY":false},{"tile":1642,"color":2,"flipX":false,"flipY":false},{"tile":1642,"color":2,"flipX":false,"flipY":false},{"tile":1642,"color":2,"flipX":false,"flipY":false}]